Workbook

Sheet Assumptions
A1: Assumption | B1: Value
A2: Growth Rate | B2: 0.1
A3: EBITDA Margin | B3: 0.2
A4: WACC | B4: 0.08
A5: Tax Rate | B5: 0.25
A6: Projection Years | B6: 5
A7: Terminal Growth Rate | B7: 0.025

Sheet Projections
A1: Year | B1: 1 | C1: 2 | D1: 3 | E1: 4 | F1: 5
A2: Revenue | B2: 1000 | C2: =B2*(1+Assumptions!$B$2) | D2: =B2*(1+Assumptions!$B$2) | E2: =B2*(1+Assumptions!$B$2) | F2: =B2*(1+Assumptions!$B$2)
A3: EBITDA | B3: =B2*Assumptions!$B$3 | C3: =B2*Assumptions!$B$3 | D3: =B2*Assumptions!$B$3 | E3: =B2*Assumptions!$B$3 | F3: =B2*Assumptions!$B$3
A4: EBIT | B4: =B3 | C4: =B3 | D4: =B3 | E4: =B3 | F4: =B3
A5: Taxes | B5: =B4*Assumptions!$B$5 | C5: =B4*Assumptions!$B$5 | D5: =B4*Assumptions!$B$5 | E5: =B4*Assumptions!$B$5 | F5: =B4*Assumptions!$B$5
A6: NOPAT | B6: =B4-B5 | C6: =B4-B5 | D6: =B4-B5 | E6: =B4-B5 | F6: =B4-B5
A7: FCF | B7: =B6 | C7: =B6 | D7: =B6 | E7: =B6 | F7: =B6

Sheet Valuation
A1: Valuation
A2: FCF Year 1 | B2: =Projections!B7
A3: FCF Year 2 | B3: =Projections!C7
A4: FCF Year 3 | B4: =Projections!D7
A5: FCF Year 4 | B5: =Projections!E7
A6: FCF Year 5 | B6: =Projections!F7
A7: Terminal Value | B7: =B6*(1+Assumptions!$B$7)/(Assumptions!$B$4-Assumptions!$B$7)
A8: Discount Factor Year 1 | B8: =1/(1+Assumptions!$B$4)^1
A9: Discount Factor Year 2 | B9: =1/(1+Assumptions!$B$4)^2
A10: Discount Factor Year 3 | B10: =1/(1+Assumptions!$B$4)^3
A11: Discount Factor Year 4 | B11: =1/(1+Assumptions!$B$4)^4
A12: Discount Factor Year 5 | B12: =1/(1+Assumptions!$B$4)^5
A13: Discount Factor Terminal | B13: =1/(1+Assumptions!$B$4)^5
A14: PV FCF Year 1 | B14: =B2*B8
A15: PV FCF Year 2 | B15: =B3*B9
A16: PV FCF Year 3 | B16: =B4*B10
A17: PV FCF Year 4 | B17: =B5*B11
A18: PV FCF Year 5 | B18: =B6*B12
A19: PV Terminal Value | B19: =B7*B13
A20: Enterprise Value | B20: =SUM(B14:B19)
