Workbook

Sheet Assumptions
A1: Assumptions
A2: Tasso Crescita | B2: 0.1
A3: Margine EBITDA | B3: 0.2
A4: WACC | B4: 0.08
A5: Aliquota Fiscale | B5: 0.25
A6: Tasso Terminale | B6: 0.025
A7: Anni | B7: 5

Sheet Projections
A1: Projections
A2: Anno | B2: 1 | C2: =B2+1 | D2: =C2+1 | E2: =D2+1 | F2: =E2+1
A3: Revenue | B3: 1000 | C3: =B3*(1+Assumptions!$B$2) | D3: =C3*(1+Assumptions!$B$2) | E3: =D3*(1+Assumptions!$B$2) | F3: =E3*(1+Assumptions!$B$2)
A4: EBITDA | B4: =B3*Assumptions!$B$3 | C4: =C3*Assumptions!$B$3 | D4: =D3*Assumptions!$B$3 | E4: =E3*Assumptions!$B$3 | F4: =F3*Assumptions!$B$3
A5: EBIT | B5: =B4 | C5: =C4 | D5: =D4 | E5: =E4 | F5: =F4
A6: Tasse | B6: =B5*Assumptions!$B$5 | C6: =C5*Assumptions!$B$5 | D6: =D5*Assumptions!$B$5 | E6: =E5*Assumptions!$B$5 | F6: =F5*Assumptions!$B$5
A7: NOPAT | B7: =B5-B6 | C7: =C5-C6 | D7: =D5-D6 | E7: =E5-E6 | F7: =F5-F6
A8: FCF | B8: =B7 | C8: =C7 | D8: =D7 | E8: =E7 | F8: =F7

Sheet Valuation
A1: Valuation
A2: Terminal Value | B2: =Projections!F8*(1+Assumptions!$B$6)/(Assumptions!$B$4-Assumptions!$B$6)
A3: Discount Factor Anno 1 | B3: =1/(1+Assumptions!$B$4)^1
A4: Discount Factor Anno 2 | B4: =1/(1+Assumptions!$B$4)^2
A5: Discount Factor Anno 3 | B5: =1/(1+Assumptions!$B$4)^3
A6: Discount Factor Anno 4 | B6: =1/(1+Assumptions!$B$4)^4
A7: Discount Factor Anno 5 | B7: =1/(1+Assumptions!$B$4)^5
A8: PV FCF Anno 1 | B8: =Projections!B8*B3
A9: PV FCF Anno 2 | B9: =Projections!C8*B4
A10: PV FCF Anno 3 | B10: =Projections!D8*B5
A11: PV FCF Anno 4 | B11: =Projections!E8*B6
A12: PV FCF Anno 5 | B12: =Projections!F8*B7
A13: PV Terminal Value | B13: =B2*B7
A14: Enterprise Value | B14: =SUM(B8:B13)
