Workbook

Sheet Assumptions
A1: MEAT CREW - Assumptions
A3: Rent (monthly) | B3: 8000
A4: Food Cost % | B4: 0.28
A5: Labor % | B5: 0.22
A6: Utilities % | B6: 0.03
A7: Marketing % | B7: 0.02
A8: Average Ticket (€) | B8: 18
A9: Daily Covers | B9: 120
A10: Capex (€) | B10: 350000
A11: EBITDA Multiple | B11: 8
A12: WACC | B12: 0.09
A13: Perpetual Growth | B13: 0.02
A14: Days Open per Month | B14: 30
... A21: Seasonality Max | B21: 0.15

Sheet Menu
A1: Category | B1: Item | C1: Single Price | D1: Menu Price
A2: Starters | B2: Mochos Bites | C2: 6.9
B3: Chicken Tenders | C3: 6.9
A4: Burgers | B4: L.A. Burger | C4: 14.5 | D4: 21.9
B5: Crispy Burger | C5: 14.5 | D5: 21.9
B6: Mac Cheese Burger | C6: 15.5 | D6: 22.9
B7: Oklahoma Burger | C7: 15 | D7: 22.4
B8: Junior Burger | C8: 8.5
A9: Sandwiches | B9: Pastrami Sandwich | C9: 19 | D9: 26.4
B10: The O.G. Sandwich | C10: 14.5 | D10: 21.9
A11: Hot Dogs | B11: Bacon Dog | C11: 8 | D11: 15.4
B12: Chili Dog | C12: 9 | D12: 16.4
A13: Sides | B13: Crispy Fries | C13: 5.5
B14: Bacon Fries | C14: 6.5
B15: Chili Fries | C15: 6.5
B16: Mac Cheese | C16: 6.5
A17: Sweets | B17: Banana Pudding | C17: 4.9
B18: Glazed Donut | C18: 2.5
A19: Milkshakes | B19: Milkshake | C19: 6
A20: Drinks | B20: Water | C20: 2
B21: Free Refill | C21: 4.5
B22: Birra Raw | C22: 5.5

Sheet Personnel
A1: Role | B1: Count | C1: Monthly Salary | D1: Total Monthly | E1: Loaded (x1.3)
A2: Store Manager | B2: 1 | C2: 3500 | D2: =B3*C3 | E2: =D3*1.3
A3: Shift Leader | B3: 2 | C3: 2400 | D3: =B4*C4 | E3: =D4*1.3
A4: Crew | B4: 6 | C4: 1500 | D4: =B5*C5 | E4: =D5*1.3
A5: Total | B5: =SUM(B3:B5) | D5: =SUM(D3:D5) | E5: =SUM(E3:E5)

Sheet Revenue
A1: 1 | B1: 2 | C1: 3 | D1: 4 | E1: 5 | F1: 6 | G1: 7 | H1: 8 | I1: 9 | J1: 10 | K1: 11 | L1: 12 | M1: 13 | N1: 14 | O1: 15 | P1: 16 | Q1: 17 | R1: 18 | S1: 19 | T1: 20 | U1: 21 | V1: 22 | W1: 23 | X1: 24 | Y1: 25 | Z1: 26 | AA1: 27 | AB1: 28 | AC1: 29 | AD1: 30 | AE1: 31 | AF1: 32 | AG1: 33 | AH1: 34 | AI1: 35 | AJ1: 36 | AK1: 37 | AL1: 38 | AM1: 39 | AN1: 40 | AO1: 41 | AP1: 42 | AQ1: 43 | AR1: 44 | AS1: 45 | AT1: 46 | AU1: 47 | AV1: 48 | AW1: 49 | AX1: 50 | AY1: 51 | AZ1: 52 | BA1: 53 | BB1: 54 | BC1: 55 | BD1: 56 | BE1: 57 | BF1: 58 | BG1: 59 | BH1: 60
A2: =1+Assumptions!$B$21*SIN((1-1)*2*PI()/12) | B2: =1+Assumptions!$B$21*SIN((2-1)*2*PI()/12) | C2: =1+Assumptions!$B$21*SIN((3-1)*2*PI()/12) | D2: =1+Assumptions!$B$21*SIN((4-1)*2*PI()/12) | E2: =1+Assumptions!$B$21*SIN((5-1)*2*PI()/12) | F2: =1+Assumptions!$B$21*SIN((6-1)*2*PI()/12) | G2: =1+Assumptions!$B$21*SIN((7-1)*2*PI()/12) | H2: =1+Assumptions!$B$21*SIN((8-1)*2*PI()/12) | I2: =1+Assumptions!$B$21*SIN((9-1)*2*PI()/12) | J2: =1+Assumptions!$B$21*SIN((10-1)*2*PI()/12) | K2: =1+Assumptions!$B$21*SIN((11-1)*2*PI()/12) | L2: =1+Assumptions!$B$21*SIN((12-1)*2*PI()/12) | M2: =1+Assumptions!$B$21*SIN((13-1)*2*PI()/12) | N2: =1+Assumptions!$B$21*SIN((14-1)*2*PI()/12) | O2: =1+Assumptions!$B$21*SIN((15-1)*2*PI()/12) | P2: =1+Assumptions!$B$21*SIN((16-1)*2*PI()/12) | Q2: =1+Assumptions!$B$21*SIN((17-1)*2*PI()/12) | R2: =1+Assumptions!$B$21*SIN((18-1)*2*PI()/12) | S2: =1+Assumptions!$B$21*SIN((19-1)*2*PI()/12) | T2: =1+Assumptions!$B$21*SIN((20-1)*2*PI()/12) | U2: =1+Assumptions!$B$21*SIN((21-1)*2*PI()/12) | V2: =1+Assumptions!$B$21*SIN((22-1)*2*PI()/12) | W2: =1+Assumptions!$B$21*SIN((23-1)*2*PI()/12) | X2: =1+Assumptions!$B$21*SIN((24-1)*2*PI()/12) | Y2: =1+Assumptions!$B$21*SIN((25-1)*2*PI()/12) | Z2: =1+Assumptions!$B$21*SIN((26-1)*2*PI()/12) | AA2: =1+Assumptions!$B$21*SIN((27-1)*2*PI()/12) | AB2: =1+Assumptions!$B$21*SIN((28-1)*2*PI()/12) | AC2: =1+Assumptions!$B$21*SIN((29-1)*2*PI()/12) | AD2: =1+Assumptions!$B$21*SIN((30-1)*2*PI()/12) | AE2: =1+Assumptions!$B$21*SIN((31-1)*2*PI()/12) | AF2: =1+Assumptions!$B$21*SIN((32-1)*2*PI()/12) | AG2: =1+Assumptions!$B$21*SIN((33-1)*2*PI()/12) | AH2: =1+Assumptions!$B$21*SIN((34-1)*2*PI()/12) | AI2: =1+Assumptions!$B$21*SIN((35-1)*2*PI()/12) | AJ2: =1+Assumptions!$B$21*SIN((36-1)*2*PI()/12) | AK2: =1+Assumptions!$B$21*SIN((37-1)*2*PI()/12) | AL2: =1+Assumptions!$B$21*SIN((38-1)*2*PI()/12) | AM2: =1+Assumptions!$B$21*SIN((39-1)*2*PI()/12) | AN2: =1+Assumptions!$B$21*SIN((40-1)*2*PI()/12) | AO2: =1+Assumptions!$B$21*SIN((41-1)*2*PI()/12) | AP2: =1+Assumptions!$B$21*SIN((42-1)*2*PI()/12) | AQ2: =1+Assumptions!$B$21*SIN((43-1)*2*PI()/12) | AR2: =1+Assumptions!$B$21*SIN((44-1)*2*PI()/12) | AS2: =1+Assumptions!$B$21*SIN((45-1)*2*PI()/12) | AT2: =1+Assumptions!$B$21*SIN((46-1)*2*PI()/12) | AU2: =1+Assumptions!$B$21*SIN((47-1)*2*PI()/12) | AV2: =1+Assumptions!$B$21*SIN((48-1)*2*PI()/12) | AW2: =1+Assumptions!$B$21*SIN((49-1)*2*PI()/12) | AX2: =1+Assumptions!$B$21*SIN((50-1)*2*PI()/12) | AY2: =1+Assumptions!$B$21*SIN((51-1)*2*PI()/12) | AZ2: =1+Assumptions!$B$21*SIN((52-1)*2*PI()/12) | BA2: =1+Assumptions!$B$21*SIN((53-1)*2*PI()/12) | BB2: =1+Assumptions!$B$21*SIN((54-1)*2*PI()/12) | BC2: =1+Assumptions!$B$21*SIN((55-1)*2*PI()/12) | BD2: =1+Assumptions!$B$21*SIN((56-1)*2*PI()/12) | BE2: =1+Assumptions!$B$21*SIN((57-1)*2*PI()/12) | BF2: =1+Assumptions!$B$21*SIN((58-1)*2*PI()/12) | BG2: =1+Assumptions!$B$21*SIN((59-1)*2*PI()/12) | BH2: =1+Assumptions!$B$21*SIN((60-1)*2*PI()/12)
A3: =Assumptions!$B$14 | B3: =Assumptions!$B$14 | C3: =Assumptions!$B$14 | D3: =Assumptions!$B$14 | E3: =Assumptions!$B$14 | F3: =Assumptions!$B$14 | G3: =Assumptions!$B$14 | H3: =Assumptions!$B$14 | ... BH3: =Assumptions!$B$14
A4: =Assumptions!$B$9 | B4: =Assumptions!$B$9 | C4: =Assumptions!$B$9 | D4: =Assumptions!$B$9 | E4: =Assumptions!$B$9 | F4: =Assumptions!$B$9 | G4: =Assumptions!$B$9 | H4: =Assumptions!$B$9 | ... L4: =Assumptions!$B$9 | M4: =Assumptions!$B$9*(1+Assumptions!$B$18) | N4: =Assumptions!$B$9*(1+Assumptions!$B$18) | O4: =Assumptions!$B$9*(1+Assumptions!$B$18) | P4: =Assumptions!$B$9*(1+Assumptions!$B$18) | Q4: =Assumptions!$B$9*(1+Assumptions!$B$18) | R4: =Assumptions!$B$9*(1+Assumptions!$B$18) | S4: =Assumptions!$B$9*(1+Assumptions!$B$18) | T4: =Assumptions!$B$9*(1+Assumptions!$B$18) | ... X4: =Assumptions!$B$9*(1+Assumptions!$B$18) | Y4: =Assumptions!$B$9*(1+Assumptions!$B$18)*(1+Assumptions!$B$19) | Z4: =Assumptions!$B$9*(1+Assumptions!$B$18)*(1+Assumptions!$B$19) | AA4: =Assumptions!$B$9*(1+Assumptions!$B$18)*(1+Assumptions!$B$19) | AB4: =Assumptions!$B$9*(1+Assumptions!$B$18)*(1+Assumptions!$B$19) | AC4: =Assumptions!$B$9*(1+Assumptions!$B$18)*(1+Assumptions!$B$19) | AD4: =Assumptions!$B$9*(1+Assumptions!$B$18)*(1+Assumptions!$B$19) | AE4: =Assumptions!$B$9*(1+Assumptions!$B$18)*(1+Assumptions!$B$19) | AF4: =Assumptions!$B$9*(1+Assumptions!$B$18)*(1+Assumptions!$B$19) | ... AJ4: =Assumptions!$B$9*(1+Assumptions!$B$18)*(1+Assumptions!$B$19) | AK4: =Assumptions!$B$9*(1+Assumptions!$B$18)*(1+Assumptions!$B$19)*(1+Assumptions!$B$20)^(FLOOR((37-1)/12,1)-2) | AL4: =Assumptions!$B$9*(1+Assumptions!$B$18)*(1+Assumptions!$B$19)*(1+Assumptions!$B$20)^(FLOOR((38-1)/12,1)-2) | AM4: =Assumptions!$B$9*(1+Assumptions!$B$18)*(1+Assumptions!$B$19)*(1+Assumptions!$B$20)^(FLOOR((39-1)/12,1)-2) | AN4: =Assumptions!$B$9*(1+Assumptions!$B$18)*(1+Assumptions!$B$19)*(1+Assumptions!$B$20)^(FLOOR((40-1)/12,1)-2) | AO4: =Assumptions!$B$9*(1+Assumptions!$B$18)*(1+Assumptions!$B$19)*(1+Assumptions!$B$20)^(FLOOR((41-1)/12,1)-2) | AP4: =Assumptions!$B$9*(1+Assumptions!$B$18)*(1+Assumptions!$B$19)*(1+Assumptions!$B$20)^(FLOOR((42-1)/12,1)-2) | AQ4: =Assumptions!$B$9*(1+Assumptions!$B$18)*(1+Assumptions!$B$19)*(1+Assumptions!$B$20)^(FLOOR((43-1)/12,1)-2) | AR4: =Assumptions!$B$9*(1+Assumptions!$B$18)*(1+Assumptions!$B$19)*(1+Assumptions!$B$20)^(FLOOR((44-1)/12,1)-2) | AS4: =Assumptions!$B$9*(1+Assumptions!$B$18)*(1+Assumptions!$B$19)*(1+Assumptions!$B$20)^(FLOOR((45-1)/12,1)-2) | AT4: =Assumptions!$B$9*(1+Assumptions!$B$18)*(1+Assumptions!$B$19)*(1+Assumptions!$B$20)^(FLOOR((46-1)/12,1)-2) | AU4: =Assumptions!$B$9*(1+Assumptions!$B$18)*(1+Assumptions!$B$19)*(1+Assumptions!$B$20)^(FLOOR((47-1)/12,1)-2) | AV4: =Assumptions!$B$9*(1+Assumptions!$B$18)*(1+Assumptions!$B$19)*(1+Assumptions!$B$20)^(FLOOR((48-1)/12,1)-2) | AW4: =Assumptions!$B$9*(1+Assumptions!$B$18)*(1+Assumptions!$B$19)*(1+Assumptions!$B$20)^(FLOOR((49-1)/12,1)-2) | AX4: =Assumptions!$B$9*(1+Assumptions!$B$18)*(1+Assumptions!$B$19)*(1+Assumptions!$B$20)^(FLOOR((50-1)/12,1)-2) | AY4: =Assumptions!$B$9*(1+Assumptions!$B$18)*(1+Assumptions!$B$19)*(1+Assumptions!$B$20)^(FLOOR((51-1)/12,1)-2) | AZ4: =Assumptions!$B$9*(1+Assumptions!$B$18)*(1+Assumptions!$B$19)*(1+Assumptions!$B$20)^(FLOOR((52-1)/12,1)-2) | BA4: =Assumptions!$B$9*(1+Assumptions!$B$18)*(1+Assumptions!$B$19)*(1+Assumptions!$B$20)^(FLOOR((53-1)/12,1)-2) | BB4: =Assumptions!$B$9*(1+Assumptions!$B$18)*(1+Assumptions!$B$19)*(1+Assumptions!$B$20)^(FLOOR((54-1)/12,1)-2) | BC4: =Assumptions!$B$9*(1+Assumptions!$B$18)*(1+Assumptions!$B$19)*(1+Assumptions!$B$20)^(FLOOR((55-1)/12,1)-2) | BD4: =Assumptions!$B$9*(1+Assumptions!$B$18)*(1+Assumptions!$B$19)*(1+Assumptions!$B$20)^(FLOOR((56-1)/12,1)-2) | BE4: =Assumptions!$B$9*(1+Assumptions!$B$18)*(1+Assumptions!$B$19)*(1+Assumptions!$B$20)^(FLOOR((57-1)/12,1)-2) | BF4: =Assumptions!$B$9*(1+Assumptions!$B$18)*(1+Assumptions!$B$19)*(1+Assumptions!$B$20)^(FLOOR((58-1)/12,1)-2) | BG4: =Assumptions!$B$9*(1+Assumptions!$B$18)*(1+Assumptions!$B$19)*(1+Assumptions!$B$20)^(FLOOR((59-1)/12,1)-2) | BH4: =Assumptions!$B$9*(1+Assumptions!$B$18)*(1+Assumptions!$B$19)*(1+Assumptions!$B$20)^(FLOOR((60-1)/12,1)-2)
A5: =Assumptions!$B$8 | B5: =Assumptions!$B$8 | C5: =Assumptions!$B$8 | D5: =Assumptions!$B$8 | E5: =Assumptions!$B$8 | F5: =Assumptions!$B$8 | G5: =Assumptions!$B$8 | H5: =Assumptions!$B$8 | ... L5: =Assumptions!$B$8 | M5: =Assumptions!$B$8*(1+Assumptions!$B$18) | N5: =Assumptions!$B$8*(1+Assumptions!$B$18) | O5: =Assumptions!$B$8*(1+Assumptions!$B$18) | P5: =Assumptions!$B$8*(1+Assumptions!$B$18) | Q5: =Assumptions!$B$8*(1+Assumptions!$B$18) | R5: =Assumptions!$B$8*(1+Assumptions!$B$18) | S5: =Assumptions!$B$8*(1+Assumptions!$B$18) | T5: =Assumptions!$B$8*(1+Assumptions!$B$18) | ... X5: =Assumptions!$B$8*(1+Assumptions!$B$18) | Y5: =Assumptions!$B$8*(1+Assumptions!$B$18)*(1+Assumptions!$B$19) | Z5: =Assumptions!$B$8*(1+Assumptions!$B$18)*(1+Assumptions!$B$19) | AA5: =Assumptions!$B$8*(1+Assumptions!$B$18)*(1+Assumptions!$B$19) | AB5: =Assumptions!$B$8*(1+Assumptions!$B$18)*(1+Assumptions!$B$19) | AC5: =Assumptions!$B$8*(1+Assumptions!$B$18)*(1+Assumptions!$B$19) | AD5: =Assumptions!$B$8*(1+Assumptions!$B$18)*(1+Assumptions!$B$19) | AE5: =Assumptions!$B$8*(1+Assumptions!$B$18)*(1+Assumptions!$B$19) | AF5: =Assumptions!$B$8*(1+Assumptions!$B$18)*(1+Assumptions!$B$19) | ... AJ5: =Assumptions!$B$8*(1+Assumptions!$B$18)*(1+Assumptions!$B$19) | AK5: =Assumptions!$B$8*(1+Assumptions!$B$18)*(1+Assumptions!$B$19)*(1+Assumptions!$B$20)^(FLOOR((37-1)/12,1)-2) | AL5: =Assumptions!$B$8*(1+Assumptions!$B$18)*(1+Assumptions!$B$19)*(1+Assumptions!$B$20)^(FLOOR((38-1)/12,1)-2) | AM5: =Assumptions!$B$8*(1+Assumptions!$B$18)*(1+Assumptions!$B$19)*(1+Assumptions!$B$20)^(FLOOR((39-1)/12,1)-2) | AN5: =Assumptions!$B$8*(1+Assumptions!$B$18)*(1+Assumptions!$B$19)*(1+Assumptions!$B$20)^(FLOOR((40-1)/12,1)-2) | AO5: =Assumptions!$B$8*(1+Assumptions!$B$18)*(1+Assumptions!$B$19)*(1+Assumptions!$B$20)^(FLOOR((41-1)/12,1)-2) | AP5: =Assumptions!$B$8*(1+Assumptions!$B$18)*(1+Assumptions!$B$19)*(1+Assumptions!$B$20)^(FLOOR((42-1)/12,1)-2) | AQ5: =Assumptions!$B$8*(1+Assumptions!$B$18)*(1+Assumptions!$B$19)*(1+Assumptions!$B$20)^(FLOOR((43-1)/12,1)-2) | AR5: =Assumptions!$B$8*(1+Assumptions!$B$18)*(1+Assumptions!$B$19)*(1+Assumptions!$B$20)^(FLOOR((44-1)/12,1)-2) | AS5: =Assumptions!$B$8*(1+Assumptions!$B$18)*(1+Assumptions!$B$19)*(1+Assumptions!$B$20)^(FLOOR((45-1)/12,1)-2) | AT5: =Assumptions!$B$8*(1+Assumptions!$B$18)*(1+Assumptions!$B$19)*(1+Assumptions!$B$20)^(FLOOR((46-1)/12,1)-2) | AU5: =Assumptions!$B$8*(1+Assumptions!$B$18)*(1+Assumptions!$B$19)*(1+Assumptions!$B$20)^(FLOOR((47-1)/12,1)-2) | AV5: =Assumptions!$B$8*(1+Assumptions!$B$18)*(1+Assumptions!$B$19)*(1+Assumptions!$B$20)^(FLOOR((48-1)/12,1)-2) | AW5: =Assumptions!$B$8*(1+Assumptions!$B$18)*(1+Assumptions!$B$19)*(1+Assumptions!$B$20)^(FLOOR((49-1)/12,1)-2) | AX5: =Assumptions!$B$8*(1+Assumptions!$B$18)*(1+Assumptions!$B$19)*(1+Assumptions!$B$20)^(FLOOR((50-1)/12,1)-2) | AY5: =Assumptions!$B$8*(1+Assumptions!$B$18)*(1+Assumptions!$B$19)*(1+Assumptions!$B$20)^(FLOOR((51-1)/12,1)-2) | AZ5: =Assumptions!$B$8*(1+Assumptions!$B$18)*(1+Assumptions!$B$19)*(1+Assumptions!$B$20)^(FLOOR((52-1)/12,1)-2) | BA5: =Assumptions!$B$8*(1+Assumptions!$B$18)*(1+Assumptions!$B$19)*(1+Assumptions!$B$20)^(FLOOR((53-1)/12,1)-2) | BB5: =Assumptions!$B$8*(1+Assumptions!$B$18)*(1+Assumptions!$B$19)*(1+Assumptions!$B$20)^(FLOOR((54-1)/12,1)-2) | BC5: =Assumptions!$B$8*(1+Assumptions!$B$18)*(1+Assumptions!$B$19)*(1+Assumptions!$B$20)^(FLOOR((55-1)/12,1)-2) | BD5: =Assumptions!$B$8*(1+Assumptions!$B$18)*(1+Assumptions!$B$19)*(1+Assumptions!$B$20)^(FLOOR((56-1)/12,1)-2) | BE5: =Assumptions!$B$8*(1+Assumptions!$B$18)*(1+Assumptions!$B$19)*(1+Assumptions!$B$20)^(FLOOR((57-1)/12,1)-2) | BF5: =Assumptions!$B$8*(1+Assumptions!$B$18)*(1+Assumptions!$B$19)*(1+Assumptions!$B$20)^(FLOOR((58-1)/12,1)-2) | BG5: =Assumptions!$B$8*(1+Assumptions!$B$18)*(1+Assumptions!$B$19)*(1+Assumptions!$B$20)^(FLOOR((59-1)/12,1)-2) | BH5: =Assumptions!$B$8*(1+Assumptions!$B$18)*(1+Assumptions!$B$19)*(1+Assumptions!$B$20)^(FLOOR((60-1)/12,1)-2)
A6: =A4*A3*A5*A2 | B6: =B4*B3*B5*B2 | C6: =C4*C3*C5*C2 | D6: =D4*D3*D5*D2 | E6: =E4*E3*E5*E2 | F6: =F4*F3*F5*F2 | G6: =G4*G3*G5*G2 | H6: =H4*H3*H5*H2 | ... BH6: =BH4*BH3*BH5*BH2
A7: Total Revenue Year 1 | B7: =SUM(B6:M6)
A8: Total Revenue Year 2 | N8: =SUM(N6:Y6)
A9: Total Revenue Year 3 | Z9: =SUM(Z6:AK6)
A10: Total Revenue Year 4 | AL10: =SUM(AL6:AW6)
A11: Total Revenue Year 5 | AX11: =SUM(AX6:BK6)

Sheet PnL
A1: 1 | B1: 2 | C1: 3 | D1: 4 | E1: 5 | F1: 6 | G1: 7 | H1: 8 | I1: 9 | J1: 10 | K1: 11 | L1: 12 | M1: 13 | N1: 14 | O1: 15 | P1: 16 | Q1: 17 | R1: 18 | S1: 19 | T1: 20 | U1: 21 | V1: 22 | W1: 23 | X1: 24 | Y1: 25 | Z1: 26 | AA1: 27 | AB1: 28 | AC1: 29 | AD1: 30 | AE1: 31 | AF1: 32 | AG1: 33 | AH1: 34 | AI1: 35 | AJ1: 36 | AK1: 37 | AL1: 38 | AM1: 39 | AN1: 40 | AO1: 41 | AP1: 42 | AQ1: 43 | AR1: 44 | AS1: 45 | AT1: 46 | AU1: 47 | AV1: 48 | AW1: 49 | AX1: 50 | AY1: 51 | AZ1: 52 | BA1: 53 | BB1: 54 | BC1: 55 | BD1: 56 | BE1: 57 | BF1: 58 | BG1: 59 | BH1: 60
A2: =Revenue!A6 | B2: =Revenue!B6 | C2: =Revenue!C6 | D2: =Revenue!D6 | E2: =Revenue!E6 | F2: =Revenue!F6 | G2: =Revenue!G6 | H2: =Revenue!H6 | ... BH2: =Revenue!BH6
A3: =A2*Assumptions!$B$4 | B3: =B2*Assumptions!$B$4 | C3: =C2*Assumptions!$B$4 | D3: =D2*Assumptions!$B$4 | E3: =E2*Assumptions!$B$4 | F3: =F2*Assumptions!$B$4 | G3: =G2*Assumptions!$B$4 | H3: =H2*Assumptions!$B$4 | ... BH3: =BH2*Assumptions!$B$4
A4: =A2*Assumptions!$B$5 | B4: =B2*Assumptions!$B$5 | C4: =C2*Assumptions!$B$5 | D4: =D2*Assumptions!$B$5 | E4: =E2*Assumptions!$B$5 | F4: =F2*Assumptions!$B$5 | G4: =G2*Assumptions!$B$5 | H4: =H2*Assumptions!$B$5 | ... BH4: =BH2*Assumptions!$B$5
A5: =Assumptions!$B$3 | B5: =Assumptions!$B$3 | C5: =Assumptions!$B$3 | D5: =Assumptions!$B$3 | E5: =Assumptions!$B$3 | F5: =Assumptions!$B$3 | G5: =Assumptions!$B$3 | H5: =Assumptions!$B$3 | ... BH5: =Assumptions!$B$3
A6: =A2*Assumptions!$B$6 | B6: =B2*Assumptions!$B$6 | C6: =C2*Assumptions!$B$6 | D6: =D2*Assumptions!$B$6 | E6: =E2*Assumptions!$B$6 | F6: =F2*Assumptions!$B$6 | G6: =G2*Assumptions!$B$6 | H6: =H2*Assumptions!$B$6 | ... BH6: =BH2*Assumptions!$B$6
A7: =A2*Assumptions!$B$7 | B7: =B2*Assumptions!$B$7 | C7: =C2*Assumptions!$B$7 | D7: =D2*Assumptions!$B$7 | E7: =E2*Assumptions!$B$7 | F7: =F2*Assumptions!$B$7 | G7: =G2*Assumptions!$B$7 | H7: =H2*Assumptions!$B$7 | ... BH7: =BH2*Assumptions!$B$7
A8: 0 | B8: 0 | C8: 0 | D8: 0 | E8: 0 | F8: 0 | G8: 0 | H8: 0 | I8: 0 | J8: 0 | K8: 0 | L8: 0 | M8: 0 | N8: 0 | O8: 0 | P8: 0 | Q8: 0 | R8: 0 | S8: 0 | T8: 0 | U8: 0 | V8: 0 | W8: 0 | X8: 0 | Y8: 0 | Z8: 0 | AA8: 0 | AB8: 0 | AC8: 0 | AD8: 0 | AE8: 0 | AF8: 0 | AG8: 0 | AH8: 0 | AI8: 0 | AJ8: 0 | AK8: 0 | AL8: 0 | AM8: 0 | AN8: 0 | AO8: 0 | AP8: 0 | AQ8: 0 | AR8: 0 | AS8: 0 | AT8: 0 | AU8: 0 | AV8: 0 | AW8: 0 | AX8: 0 | AY8: 0 | AZ8: 0 | BA8: 0 | BB8: 0 | BC8: 0 | BD8: 0 | BE8: 0 | BF8: 0 | BG8: 0 | BH8: 0
A9: =A2-A3-A4-A5-A6-A7-A8 | B9: =B2-B3-B4-B5-B6-B7-B8 | C9: =C2-C3-C4-C5-C6-C7-C8 | D9: =D2-D3-D4-D5-D6-D7-D8 | E9: =E2-E3-E4-E5-E6-E7-E8 | F9: =F2-F3-F4-F5-F6-F7-F8 | G9: =G2-G3-G4-G5-G6-G7-G8 | H9: =H2-H3-H4-H5-H6-H7-H8 | ... BH9: =BH2-BH3-BH4-BH5-BH6-BH7-BH8
A10: =Assumptions!$B$10/Assumptions!$B$17/12 | B10: =Assumptions!$B$10/Assumptions!$B$17/12 | C10: =Assumptions!$B$10/Assumptions!$B$17/12 | D10: =Assumptions!$B$10/Assumptions!$B$17/12 | E10: =Assumptions!$B$10/Assumptions!$B$17/12 | F10: =Assumptions!$B$10/Assumptions!$B$17/12 | G10: =Assumptions!$B$10/Assumptions!$B$17/12 | H10: =Assumptions!$B$10/Assumptions!$B$17/12 | ... BH10: =Assumptions!$B$10/Assumptions!$B$17/12
A11: =A9-A10 | B11: =B9-B10 | C11: =C9-C10 | D11: =D9-D10 | E11: =E9-E10 | F11: =F9-F10 | G11: =G9-G10 | H11: =H9-H10 | ... BH11: =BH9-BH10
A12: =(A11)*(Assumptions!$B$15+Assumptions!$B$16) | B12: =(B11)*(Assumptions!$B$15+Assumptions!$B$16) | C12: =(C11)*(Assumptions!$B$15+Assumptions!$B$16) | D12: =(D11)*(Assumptions!$B$15+Assumptions!$B$16) | E12: =(E11)*(Assumptions!$B$15+Assumptions!$B$16) | F12: =(F11)*(Assumptions!$B$15+Assumptions!$B$16) | G12: =(G11)*(Assumptions!$B$15+Assumptions!$B$16) | H12: =(H11)*(Assumptions!$B$15+Assumptions!$B$16) | ... BH12: =(BH11)*(Assumptions!$B$15+Assumptions!$B$16)
A13: =A11-A12 | B13: =B11-B12 | C13: =C11-C12 | D13: =D11-D12 | E13: =E11-E12 | F13: =F11-F12 | G13: =G11-G12 | H13: =H11-H12 | ... BH13: =BH11-BH12
BM14: Year 1 | BN14: Year 2 | BO14: Year 3 | BP14: Year 4 | BQ14: Year 5
A15: Revenue | BM15: =SUM(B2:M2) | BN15: =SUM(N2:Y2) | BO15: =SUM(Z2:AK2) | BP15: =SUM(AL2:AW2) | BQ15: =SUM(AX2:BK2)
A16: Food Cost | BM16: =SUM(B3:M3) | BN16: =SUM(N3:Y3) | BO16: =SUM(Z3:AK3) | BP16: =SUM(AL3:AW3) | BQ16: =SUM(AX3:BK3)
A17: Labor | BM17: =SUM(B4:M4) | BN17: =SUM(N4:Y4) | BO17: =SUM(Z4:AK4) | BP17: =SUM(AL4:AW4) | BQ17: =SUM(AX4:BK4)
A18: Rent | BM18: =SUM(B5:M5) | BN18: =SUM(N5:Y5) | BO18: =SUM(Z5:AK5) | BP18: =SUM(AL5:AW5) | BQ18: =SUM(AX5:BK5)
A19: Utilities | BM19: =SUM(B6:M6) | BN19: =SUM(N6:Y6) | BO19: =SUM(Z6:AK6) | BP19: =SUM(AL6:AW6) | BQ19: =SUM(AX6:BK6)
A20: Marketing | BM20: =SUM(B7:M7) | BN20: =SUM(N7:Y7) | BO20: =SUM(Z7:AK7) | BP20: =SUM(AL7:AW7) | BQ20: =SUM(AX7:BK7)
A21: Other | BM21: =SUM(B8:M8) | BN21: =SUM(N8:Y8) | BO21: =SUM(Z8:AK8) | BP21: =SUM(AL8:AW8) | BQ21: =SUM(AX8:BK8)
A22: EBITDA | BM22: =SUM(B9:M9) | BN22: =SUM(N9:Y9) | BO22: =SUM(Z9:AK9) | BP22: =SUM(AL9:AW9) | BQ22: =SUM(AX9:BK9)
A23: Depreciation | BM23: =SUM(B10:M10) | BN23: =SUM(N10:Y10) | BO23: =SUM(Z10:AK10) | BP23: =SUM(AL10:AW10) | BQ23: =SUM(AX10:BK10)
A24: EBIT | BM24: =SUM(B11:M11) | BN24: =SUM(N11:Y11) | BO24: =SUM(Z11:AK11) | BP24: =SUM(AL11:AW11) | BQ24: =SUM(AX11:BK11)
A25: Taxes | BM25: =SUM(B12:M12) | BN25: =SUM(N12:Y12) | BO25: =SUM(Z12:AK12) | BP25: =SUM(AL12:AW12) | BQ25: =SUM(AX12:BK12)
A26: Net Income | BM26: =SUM(B13:M13) | BN26: =SUM(N13:Y13) | BO26: =SUM(Z13:AK13) | BP26: =SUM(AL13:AW13) | BQ26: =SUM(AX13:BK13)

Sheet CashFlow
A1: Cash Flow Statement
A2: Year | B2: Year 1 | C2: Year 2 | D2: Year 3 | E2: Year 4 | F2: Year 5
A3: Net Income | B3: =PnL!BM27 | C3: =PnL!BN27 | D3: =PnL!BO27 | E3: =PnL!BP27 | F3: =PnL!BQ27
A4: Depreciation | B4: =PnL!BM25 | C4: =PnL!BN25 | D4: =PnL!BO25 | E4: =PnL!BP25 | F4: =PnL!BQ25
A5: Change in WC | B5: 0 | C5: 0 | D5: 0 | E5: 0 | F5: 0
A6: Operating Cash Flow | B6: =B3+B4+B5 | C6: =C3+C4+C5 | D6: =D3+D4+D5 | E6: =E3+E4+E5 | F6: =F3+F4+F5
A7: Capex | B7: =-Assumptions!$B$10 | C7: 0 | D7: 0 | E7: 0 | F7: 0
A8: Free Cash Flow | B8: =B6+B7 | C8: =C6+C7 | D8: =D6+D7 | E8: =E6+E7 | F8: =F6+F7
A9: Cumulative FCF | B9: =B8 | C9: =B9+C8 | D9: =C9+D8 | E9: =D9+E8 | F9: =E9+F8

Sheet BreakEven
A1: Monthly Break-Even Analysis
A2: Fixed Costs (Rent + Labor + Other) | B2: =Assumptions!$B$3+Personnel!$E$6+0
A3: Variable Cost % (Food + Utilities + Marketing) | B3: =Assumptions!$B$4+Assumptions!$B$6+Assumptions!$B$7
A4: Contribution Margin % | B4: =1-B3
A5: Break-Even Revenue (monthly) | B5: =B2/B4
A6: Break-Even Covers per Day | B6: =B5/(Assumptions!$B$14*Assumptions!$B$8)

Sheet ScaleUp
A1: Scale-Up to 4 Cities
A2: City | B2: Covers per Day | C2: Average Ticket | D2: Monthly Revenue | E2: Annual Revenue | F2: EBITDA Margin | G2: Annual EBITDA | H2: Capex | I2: Payback (years)
A3: Milan (Base) | B3: =Assumptions!$B$9 | C3: =Assumptions!$B$8 | D3: =B3*Assumptions!$B$14*C3 | E3: =D3*12 | F3: =1-Assumptions!$B$4-Assumptions!$B$5-Assumptions!$B$6-Assumptions!$B$7 | G3: =E3*F3 | H3: =Assumptions!$B$10 | I3: =H3/G3
A4: Rome | B4: =Assumptions!$B$9*0.9 | C4: =Assumptions!$B$8*1.05 | D4: =B4*Assumptions!$B$14*C4 | E4: =D4*12 | F4: =F3 | G4: =E4*F4 | H4: =Assumptions!$B$10*1.1 | I4: =H4/G4
A5: Naples | B5: =Assumptions!$B$9*0.8 | C5: =Assumptions!$B$8*0.95 | D5: =B5*Assumptions!$B$14*C5 | E5: =D5*12 | F5: =F3 | G5: =E5*F5 | H5: =Assumptions!$B$10*0.9 | I5: =H5/G5
A6: Turin | B6: =Assumptions!$B$9*0.85 | C6: =Assumptions!$B$8*1.0 | D6: =B6*Assumptions!$B$14*C6 | E6: =D6*12 | F6: =F3 | G6: =E6*F6 | H6: =Assumptions!$B$10*0.95 | I6: =H6/G6
A7: Total | B7: =SUM(B3:B6) | C7: =AVERAGE(C3:C6) | D7: =SUM(D3:D6) | E7: =SUM(E3:E6) | F7: =AVERAGE(F3:F6) | G7: =SUM(G3:G6) | H7: =SUM(H3:H6) | I7: =H7/G7

Sheet Valuation
A1: DCF Valuation
A2: Year | B2: FCF | C2: Discount Factor | D2: PV of FCF
A3: 1 | B3: =CashFlow!B8 | C3: =1/(1+Assumptions!$B$12)^A3 | D3: =B3*C3
A4: 2 | B4: =CashFlow!C8 | C4: =1/(1+Assumptions!$B$12)^A4 | D4: =B4*C4
A5: 3 | B5: =CashFlow!D8 | C5: =1/(1+Assumptions!$B$12)^A5 | D5: =B5*C5
A6: 4 | B6: =CashFlow!E8 | C6: =1/(1+Assumptions!$B$12)^A6 | D6: =B6*C6
A7: 5 | B7: =CashFlow!F8 | C7: =1/(1+Assumptions!$B$12)^A7 | D7: =B7*C7
A8: Terminal Value | B8: =CashFlow!F8*(1+Assumptions!$B$13)/(Assumptions!$B$12-Assumptions!$B$13) | C8: =1/(1+Assumptions!$B$12)^5 | D8: =B8*C8
A9: Enterprise Value | D9: =SUM(D3:D8)
A10: Less: Net Debt | D10: 0
A11: Equity Value | D11: =D9-D10
A12: IRR | D12: =IRR(B3:B7,-Assumptions!$B$10)

Sheet Sensitivity
A1: EBITDA Sensitivity (Annual)
A2: Covers per Day \ Ticket | B2: =Assumptions!$B$8*0.9 | C2: =Assumptions!$B$8*0.95 | D2: =Assumptions!$B$8 | E2: =Assumptions!$B$8*1.05 | F2: =Assumptions!$B$8*1.1
A3: =Assumptions!$B$9*0.9 | B3: =((A3*Assumptions!$B$14*B$2*(1-Assumptions!$B$4-Assumptions!$B$6-Assumptions!$B$7))-(Assumptions!$B$3+Personnel!$E$6))*12 | C3: =((A3*Assumptions!$B$14*C$2*(1-Assumptions!$B$4-Assumptions!$B$6-Assumptions!$B$7))-(Assumptions!$B$3+Personnel!$E$6))*12 | D3: =((A3*Assumptions!$B$14*D$2*(1-Assumptions!$B$4-Assumptions!$B$6-Assumptions!$B$7))-(Assumptions!$B$3+Personnel!$E$6))*12 | E3: =((A3*Assumptions!$B$14*E$2*(1-Assumptions!$B$4-Assumptions!$B$6-Assumptions!$B$7))-(Assumptions!$B$3+Personnel!$E$6))*12 | F3: =((A3*Assumptions!$B$14*F$2*(1-Assumptions!$B$4-Assumptions!$B$6-Assumptions!$B$7))-(Assumptions!$B$3+Personnel!$E$6))*12
A4: =Assumptions!$B$9*0.95 | B4: =((A4*Assumptions!$B$14*B$2*(1-Assumptions!$B$4-Assumptions!$B$6-Assumptions!$B$7))-(Assumptions!$B$3+Personnel!$E$6))*12 | C4: =((A4*Assumptions!$B$14*C$2*(1-Assumptions!$B$4-Assumptions!$B$6-Assumptions!$B$7))-(Assumptions!$B$3+Personnel!$E$6))*12 | D4: =((A4*Assumptions!$B$14*D$2*(1-Assumptions!$B$4-Assumptions!$B$6-Assumptions!$B$7))-(Assumptions!$B$3+Personnel!$E$6))*12 | E4: =((A4*Assumptions!$B$14*E$2*(1-Assumptions!$B$4-Assumptions!$B$6-Assumptions!$B$7))-(Assumptions!$B$3+Personnel!$E$6))*12 | F4: =((A4*Assumptions!$B$14*F$2*(1-Assumptions!$B$4-Assumptions!$B$6-Assumptions!$B$7))-(Assumptions!$B$3+Personnel!$E$6))*12
A5: =Assumptions!$B$9 | B5: =((A5*Assumptions!$B$14*B$2*(1-Assumptions!$B$4-Assumptions!$B$6-Assumptions!$B$7))-(Assumptions!$B$3+Personnel!$E$6))*12 | C5: =((A5*Assumptions!$B$14*C$2*(1-Assumptions!$B$4-Assumptions!$B$6-Assumptions!$B$7))-(Assumptions!$B$3+Personnel!$E$6))*12 | D5: =((A5*Assumptions!$B$14*D$2*(1-Assumptions!$B$4-Assumptions!$B$6-Assumptions!$B$7))-(Assumptions!$B$3+Personnel!$E$6))*12 | E5: =((A5*Assumptions!$B$14*E$2*(1-Assumptions!$B$4-Assumptions!$B$6-Assumptions!$B$7))-(Assumptions!$B$3+Personnel!$E$6))*12 | F5: =((A5*Assumptions!$B$14*F$2*(1-Assumptions!$B$4-Assumptions!$B$6-Assumptions!$B$7))-(Assumptions!$B$3+Personnel!$E$6))*12
A6: =Assumptions!$B$9*1.05 | B6: =((A6*Assumptions!$B$14*B$2*(1-Assumptions!$B$4-Assumptions!$B$6-Assumptions!$B$7))-(Assumptions!$B$3+Personnel!$E$6))*12 | C6: =((A6*Assumptions!$B$14*C$2*(1-Assumptions!$B$4-Assumptions!$B$6-Assumptions!$B$7))-(Assumptions!$B$3+Personnel!$E$6))*12 | D6: =((A6*Assumptions!$B$14*D$2*(1-Assumptions!$B$4-Assumptions!$B$6-Assumptions!$B$7))-(Assumptions!$B$3+Personnel!$E$6))*12 | E6: =((A6*Assumptions!$B$14*E$2*(1-Assumptions!$B$4-Assumptions!$B$6-Assumptions!$B$7))-(Assumptions!$B$3+Personnel!$E$6))*12 | F6: =((A6*Assumptions!$B$14*F$2*(1-Assumptions!$B$4-Assumptions!$B$6-Assumptions!$B$7))-(Assumptions!$B$3+Personnel!$E$6))*12
A7: =Assumptions!$B$9*1.1 | B7: =((A7*Assumptions!$B$14*B$2*(1-Assumptions!$B$4-Assumptions!$B$6-Assumptions!$B$7))-(Assumptions!$B$3+Personnel!$E$6))*12 | C7: =((A7*Assumptions!$B$14*C$2*(1-Assumptions!$B$4-Assumptions!$B$6-Assumptions!$B$7))-(Assumptions!$B$3+Personnel!$E$6))*12 | D7: =((A7*Assumptions!$B$14*D$2*(1-Assumptions!$B$4-Assumptions!$B$6-Assumptions!$B$7))-(Assumptions!$B$3+Personnel!$E$6))*12 | E7: =((A7*Assumptions!$B$14*E$2*(1-Assumptions!$B$4-Assumptions!$B$6-Assumptions!$B$7))-(Assumptions!$B$3+Personnel!$E$6))*12 | F7: =((A7*Assumptions!$B$14*F$2*(1-Assumptions!$B$4-Assumptions!$B$6-Assumptions!$B$7))-(Assumptions!$B$3+Personnel!$E$6))*12
