Workbook

Sheet Assumptions
A1: Assumptions
A2: Item | B2: Value
A3: Affitto mensile Milano | B3: 8000
A4: Food Cost % | B4: 0.28
A5: Labor Cost % | B5: 0.22
A6: Utenze % | B6: 0.03
A7: Marketing % | B7: 0.02
A8: Scontrino medio € | B8: 18
A9: Coperti/giorno | B9: 120
A10: Capex apertura € | B10: 350000
A11: Multiplo EBITDA exit | B11: 8
A12: Giorni apertura/mese | B12: 30
A13: WACC | B13: 0.09
A14: Crescita perpetua | B14: 0.02
... A17: Loaded labor % | B17: 1.3

Sheet Menu
A1: Category | B1: Item | C1: Price Single | D1: Price Menu
A2: Starters | B2: MOCHO'S BITES | C2: 6.9
B3: CHICKEN TENDERS | C3: 6.9
A4: Burger | B4: L.A. | C4: 14.5 | D4: 21.9
B5: CRISPY | C5: 14.5 | D5: 21.9
B6: MAC 'N' CHEESE | C6: 15.5 | D6: 22.9
B7: OKLAHOMA | C7: 15 | D7: 22.4
B8: JUNIOR | C8: 8.5
A9: Sandwiches | B9: PASTRAMI | C9: 19 | D9: 26.4
B10: THE O.G. | C10: 14.5 | D10: 21.9
A11: Hot Dogs | B11: BACON DOG | C11: 8 | D11: 15.4
B12: CHILI DOG | C12: 9 | D12: 16.4
A13: Sides | B13: CRISPY FRIES | C13: 5.5
B14: BACON FRIES | C14: 6.5
B15: CHILI FRIES | C15: 6.5
B16: MAC 'N' CHEESE | C16: 6.5
A17: Sweets | B17: BANANA PUDDING | C17: 4.9
B18: GLAZED DONUT | C18: 2.5
A19: Milkshakes | B19: Vaniglia, PB, Banana, Fragola, Cioccolato, Oreo | C19: 6
A20: Drinks | B20: Acqua | C20: 2
B21: FREE REFILL | C21: 4.5
B22: Birra Raw | C22: 5.5

Sheet Personnel
A1: Role | B1: Monthly Salary | C1: Count | D1: Total Monthly | E1: Annual Loaded
A2: Store Manager | B2: 3500 | C2: 1 | D2: =B2*C2 | E2: =D2*12*Assumptions!B17
A3: Shift Leader | B3: 2400 | C3: 2 | D3: =B3*C3 | E3: =D3*12*Assumptions!B17
A4: Crew | B4: 1500 | C4: 6 | D4: =B4*C4 | E4: =D4*12*Assumptions!B17
A5: Total | D5: =SUM(D2:D4) | E5: =SUM(E2:E4)

Sheet Revenue
A1: Month | B1: Year | C1: Coperti/giorno | D1: Scontrino medio | E1: Giorni | F1: Seasonality Factor | G1: Revenue
A2: Jan-2024 | B2: 2024 | C2: =Assumptions!B9*1 | D2: =Assumptions!B8*1 | E2: =Assumptions!B12 | F2: 0.87009619 | G2: =C2*D2*E2*F2
A3: Feb-2024 | B3: 2024 | C3: =Assumptions!B9*1 | D3: =Assumptions!B8*1 | E3: =Assumptions!B12 | F3: 0.925 | G3: =C3*D3*E3*F3
A4: Mar-2024 | B4: 2024 | C4: =Assumptions!B9*1 | D4: =Assumptions!B8*1 | E4: =Assumptions!B12 | F4: 1 | G4: =C4*D4*E4*F4
A5: Apr-2024 | B5: 2024 | C5: =Assumptions!B9*1 | D5: =Assumptions!B8*1 | E5: =Assumptions!B12 | F5: 1.075 | G5: =C5*D5*E5*F5
A6: May-2024 | B6: 2024 | C6: =Assumptions!B9*1 | D6: =Assumptions!B8*1 | E6: =Assumptions!B12 | F6: 1.1299038 | G6: =C6*D6*E6*F6
A7: Jun-2024 | B7: 2024 | C7: =Assumptions!B9*1 | D7: =Assumptions!B8*1 | E7: =Assumptions!B12 | F7: 1.15 | G7: =C7*D7*E7*F7
A8: Jul-2024 | B8: 2024 | C8: =Assumptions!B9*1 | D8: =Assumptions!B8*1 | E8: =Assumptions!B12 | F8: 1.1299038 | G8: =C8*D8*E8*F8
A9: Aug-2024 | B9: 2024 | C9: =Assumptions!B9*1 | D9: =Assumptions!B8*1 | E9: =Assumptions!B12 | F9: 1.075 | G9: =C9*D9*E9*F9
A10: Sep-2024 | B10: 2024 | C10: =Assumptions!B9*1 | D10: =Assumptions!B8*1 | E10: =Assumptions!B12 | F10: 1 | G10: =C10*D10*E10*F10
A11: Oct-2024 | B11: 2024 | C11: =Assumptions!B9*1 | D11: =Assumptions!B8*1 | E11: =Assumptions!B12 | F11: 0.925 | G11: =C11*D11*E11*F11
A12: Nov-2024 | B12: 2024 | C12: =Assumptions!B9*1 | D12: =Assumptions!B8*1 | E12: =Assumptions!B12 | F12: 0.87009619 | G12: =C12*D12*E12*F12
A13: Dec-2024 | B13: 2024 | C13: =Assumptions!B9*1 | D13: =Assumptions!B8*1 | E13: =Assumptions!B12 | F13: 0.85 | G13: =C13*D13*E13*F13
A14: Jan-2025 | B14: 2025 | C14: =Assumptions!B9*1.15 | D14: =Assumptions!B8*1.15 | E14: =Assumptions!B12 | F14: 0.87009619 | G14: =C14*D14*E14*F14
A15: Feb-2025 | B15: 2025 | C15: =Assumptions!B9*1.15 | D15: =Assumptions!B8*1.15 | E15: =Assumptions!B12 | F15: 0.925 | G15: =C15*D15*E15*F15
A16: Mar-2025 | B16: 2025 | C16: =Assumptions!B9*1.15 | D16: =Assumptions!B8*1.15 | E16: =Assumptions!B12 | F16: 1 | G16: =C16*D16*E16*F16
A17: Apr-2025 | B17: 2025 | C17: =Assumptions!B9*1.15 | D17: =Assumptions!B8*1.15 | E17: =Assumptions!B12 | F17: 1.075 | G17: =C17*D17*E17*F17
A18: May-2025 | B18: 2025 | C18: =Assumptions!B9*1.15 | D18: =Assumptions!B8*1.15 | E18: =Assumptions!B12 | F18: 1.1299038 | G18: =C18*D18*E18*F18
A19: Jun-2025 | B19: 2025 | C19: =Assumptions!B9*1.15 | D19: =Assumptions!B8*1.15 | E19: =Assumptions!B12 | F19: 1.15 | G19: =C19*D19*E19*F19
A20: Jul-2025 | B20: 2025 | C20: =Assumptions!B9*1.15 | D20: =Assumptions!B8*1.15 | E20: =Assumptions!B12 | F20: 1.1299038 | G20: =C20*D20*E20*F20
A21: Aug-2025 | B21: 2025 | C21: =Assumptions!B9*1.15 | D21: =Assumptions!B8*1.15 | E21: =Assumptions!B12 | F21: 1.075 | G21: =C21*D21*E21*F21
A22: Sep-2025 | B22: 2025 | C22: =Assumptions!B9*1.15 | D22: =Assumptions!B8*1.15 | E22: =Assumptions!B12 | F22: 1 | G22: =C22*D22*E22*F22
A23: Oct-2025 | B23: 2025 | C23: =Assumptions!B9*1.15 | D23: =Assumptions!B8*1.15 | E23: =Assumptions!B12 | F23: 0.925 | G23: =C23*D23*E23*F23
A24: Nov-2025 | B24: 2025 | C24: =Assumptions!B9*1.15 | D24: =Assumptions!B8*1.15 | E24: =Assumptions!B12 | F24: 0.87009619 | G24: =C24*D24*E24*F24
A25: Dec-2025 | B25: 2025 | C25: =Assumptions!B9*1.15 | D25: =Assumptions!B8*1.15 | E25: =Assumptions!B12 | F25: 0.85 | G25: =C25*D25*E25*F25
A26: Jan-2026 | B26: 2026 | C26: =Assumptions!B9*1.265 | D26: =Assumptions!B8*1.265 | E26: =Assumptions!B12 | F26: 0.87009619 | G26: =C26*D26*E26*F26
A27: Feb-2026 | B27: 2026 | C27: =Assumptions!B9*1.265 | D27: =Assumptions!B8*1.265 | E27: =Assumptions!B12 | F27: 0.925 | G27: =C27*D27*E27*F27
A28: Mar-2026 | B28: 2026 | C28: =Assumptions!B9*1.265 | D28: =Assumptions!B8*1.265 | E28: =Assumptions!B12 | F28: 1 | G28: =C28*D28*E28*F28
A29: Apr-2026 | B29: 2026 | C29: =Assumptions!B9*1.265 | D29: =Assumptions!B8*1.265 | E29: =Assumptions!B12 | F29: 1.075 | G29: =C29*D29*E29*F29
A30: May-2026 | B30: 2026 | C30: =Assumptions!B9*1.265 | D30: =Assumptions!B8*1.265 | E30: =Assumptions!B12 | F30: 1.1299038 | G30: =C30*D30*E30*F30
A31: Jun-2026 | B31: 2026 | C31: =Assumptions!B9*1.265 | D31: =Assumptions!B8*1.265 | E31: =Assumptions!B12 | F31: 1.15 | G31: =C31*D31*E31*F31
A32: Jul-2026 | B32: 2026 | C32: =Assumptions!B9*1.265 | D32: =Assumptions!B8*1.265 | E32: =Assumptions!B12 | F32: 1.1299038 | G32: =C32*D32*E32*F32
A33: Aug-2026 | B33: 2026 | C33: =Assumptions!B9*1.265 | D33: =Assumptions!B8*1.265 | E33: =Assumptions!B12 | F33: 1.075 | G33: =C33*D33*E33*F33
A34: Sep-2026 | B34: 2026 | C34: =Assumptions!B9*1.265 | D34: =Assumptions!B8*1.265 | E34: =Assumptions!B12 | F34: 1 | G34: =C34*D34*E34*F34
A35: Oct-2026 | B35: 2026 | C35: =Assumptions!B9*1.265 | D35: =Assumptions!B8*1.265 | E35: =Assumptions!B12 | F35: 0.925 | G35: =C35*D35*E35*F35
A36: Nov-2026 | B36: 2026 | C36: =Assumptions!B9*1.265 | D36: =Assumptions!B8*1.265 | E36: =Assumptions!B12 | F36: 0.87009619 | G36: =C36*D36*E36*F36
A37: Dec-2026 | B37: 2026 | C37: =Assumptions!B9*1.265 | D37: =Assumptions!B8*1.265 | E37: =Assumptions!B12 | F37: 0.85 | G37: =C37*D37*E37*F37
A38: Jan-2027 | B38: 2027 | C38: =Assumptions!B9*1.32825 | D38: =Assumptions!B8*1.32825 | E38: =Assumptions!B12 | F38: 0.87009619 | G38: =C38*D38*E38*F38
A39: Feb-2027 | B39: 2027 | C39: =Assumptions!B9*1.32825 | D39: =Assumptions!B8*1.32825 | E39: =Assumptions!B12 | F39: 0.925 | G39: =C39*D39*E39*F39
A40: Mar-2027 | B40: 2027 | C40: =Assumptions!B9*1.32825 | D40: =Assumptions!B8*1.32825 | E40: =Assumptions!B12 | F40: 1 | G40: =C40*D40*E40*F40
A41: Apr-2027 | B41: 2027 | C41: =Assumptions!B9*1.32825 | D41: =Assumptions!B8*1.32825 | E41: =Assumptions!B12 | F41: 1.075 | G41: =C41*D41*E41*F41
A42: May-2027 | B42: 2027 | C42: =Assumptions!B9*1.32825 | D42: =Assumptions!B8*1.32825 | E42: =Assumptions!B12 | F42: 1.1299038 | G42: =C42*D42*E42*F42
A43: Jun-2027 | B43: 2027 | C43: =Assumptions!B9*1.32825 | D43: =Assumptions!B8*1.32825 | E43: =Assumptions!B12 | F43: 1.15 | G43: =C43*D43*E43*F43
A44: Jul-2027 | B44: 2027 | C44: =Assumptions!B9*1.32825 | D44: =Assumptions!B8*1.32825 | E44: =Assumptions!B12 | F44: 1.1299038 | G44: =C44*D44*E44*F44
A45: Aug-2027 | B45: 2027 | C45: =Assumptions!B9*1.32825 | D45: =Assumptions!B8*1.32825 | E45: =Assumptions!B12 | F45: 1.075 | G45: =C45*D45*E45*F45
A46: Sep-2027 | B46: 2027 | C46: =Assumptions!B9*1.32825 | D46: =Assumptions!B8*1.32825 | E46: =Assumptions!B12 | F46: 1 | G46: =C46*D46*E46*F46
A47: Oct-2027 | B47: 2027 | C47: =Assumptions!B9*1.32825 | D47: =Assumptions!B8*1.32825 | E47: =Assumptions!B12 | F47: 0.925 | G47: =C47*D47*E47*F47
A48: Nov-2027 | B48: 2027 | C48: =Assumptions!B9*1.32825 | D48: =Assumptions!B8*1.32825 | E48: =Assumptions!B12 | F48: 0.87009619 | G48: =C48*D48*E48*F48
A49: Dec-2027 | B49: 2027 | C49: =Assumptions!B9*1.32825 | D49: =Assumptions!B8*1.32825 | E49: =Assumptions!B12 | F49: 0.85 | G49: =C49*D49*E49*F49
A50: Jan-2028 | B50: 2028 | C50: =Assumptions!B9*1.3946625 | D50: =Assumptions!B8*1.3946625 | E50: =Assumptions!B12 | F50: 0.87009619 | G50: =C50*D50*E50*F50
A51: Feb-2028 | B51: 2028 | C51: =Assumptions!B9*1.3946625 | D51: =Assumptions!B8*1.3946625 | E51: =Assumptions!B12 | F51: 0.925 | G51: =C51*D51*E51*F51
A52: Mar-2028 | B52: 2028 | C52: =Assumptions!B9*1.3946625 | D52: =Assumptions!B8*1.3946625 | E52: =Assumptions!B12 | F52: 1 | G52: =C52*D52*E52*F52
A53: Apr-2028 | B53: 2028 | C53: =Assumptions!B9*1.3946625 | D53: =Assumptions!B8*1.3946625 | E53: =Assumptions!B12 | F53: 1.075 | G53: =C53*D53*E53*F53
A54: May-2028 | B54: 2028 | C54: =Assumptions!B9*1.3946625 | D54: =Assumptions!B8*1.3946625 | E54: =Assumptions!B12 | F54: 1.1299038 | G54: =C54*D54*E54*F54
A55: Jun-2028 | B55: 2028 | C55: =Assumptions!B9*1.3946625 | D55: =Assumptions!B8*1.3946625 | E55: =Assumptions!B12 | F55: 1.15 | G55: =C55*D55*E55*F55
A56: Jul-2028 | B56: 2028 | C56: =Assumptions!B9*1.3946625 | D56: =Assumptions!B8*1.3946625 | E56: =Assumptions!B12 | F56: 1.1299038 | G56: =C56*D56*E56*F56
A57: Aug-2028 | B57: 2028 | C57: =Assumptions!B9*1.3946625 | D57: =Assumptions!B8*1.3946625 | E57: =Assumptions!B12 | F57: 1.075 | G57: =C57*D57*E57*F57
A58: Sep-2028 | B58: 2028 | C58: =Assumptions!B9*1.3946625 | D58: =Assumptions!B8*1.3946625 | E58: =Assumptions!B12 | F58: 1 | G58: =C58*D58*E58*F58
A59: Oct-2028 | B59: 2028 | C59: =Assumptions!B9*1.3946625 | D59: =Assumptions!B8*1.3946625 | E59: =Assumptions!B12 | F59: 0.925 | G59: =C59*D59*E59*F59
A60: Nov-2028 | B60: 2028 | C60: =Assumptions!B9*1.3946625 | D60: =Assumptions!B8*1.3946625 | E60: =Assumptions!B12 | F60: 0.87009619 | G60: =C60*D60*E60*F60
A61: Dec-2028 | B61: 2028 | C61: =Assumptions!B9*1.3946625 | D61: =Assumptions!B8*1.3946625 | E61: =Assumptions!B12 | F61: 0.85 | G61: =C61*D61*E61*F61

Sheet PnL
A1: Month | B1: Revenue | C1: Food Cost | D1: Labor Cost | E1: Utenze | F1: Marketing | G1: Affitto | H1: EBITDA | I1: Ammortamenti | J1: EBIT | K1: Taxes | L1: Net Income
A2: =Revenue!A2 | B2: =Revenue!G2 | C2: =B2*Assumptions!B4 | D2: =B2*Assumptions!B5 | E2: =B2*Assumptions!B6 | F2: =B2*Assumptions!B7 | G2: =Assumptions!B3 | H2: =B2-SUM(C2:G2) | I2: =Assumptions!B10/60 | J2: =H2-I2 | K2: =J2*(Assumptions!B15+Assumptions!B16) | L2: =J2-K2
A3: =Revenue!A3 | B3: =Revenue!G3 | C3: =B3*Assumptions!B4 | D3: =B3*Assumptions!B5 | E3: =B3*Assumptions!B6 | F3: =B3*Assumptions!B7 | G3: =Assumptions!B3 | H3: =B3-SUM(C3:G3) | I3: =Assumptions!B10/60 | J3: =H3-I3 | K3: =J3*(Assumptions!B15+Assumptions!B16) | L3: =J3-K3
A4: =Revenue!A4 | B4: =Revenue!G4 | C4: =B4*Assumptions!B4 | D4: =B4*Assumptions!B5 | E4: =B4*Assumptions!B6 | F4: =B4*Assumptions!B7 | G4: =Assumptions!B3 | H4: =B4-SUM(C4:G4) | I4: =Assumptions!B10/60 | J4: =H4-I4 | K4: =J4*(Assumptions!B15+Assumptions!B16) | L4: =J4-K4
A5: =Revenue!A5 | B5: =Revenue!G5 | C5: =B5*Assumptions!B4 | D5: =B5*Assumptions!B5 | E5: =B5*Assumptions!B6 | F5: =B5*Assumptions!B7 | G5: =Assumptions!B3 | H5: =B5-SUM(C5:G5) | I5: =Assumptions!B10/60 | J5: =H5-I5 | K5: =J5*(Assumptions!B15+Assumptions!B16) | L5: =J5-K5
A6: =Revenue!A6 | B6: =Revenue!G6 | C6: =B6*Assumptions!B4 | D6: =B6*Assumptions!B5 | E6: =B6*Assumptions!B6 | F6: =B6*Assumptions!B7 | G6: =Assumptions!B3 | H6: =B6-SUM(C6:G6) | I6: =Assumptions!B10/60 | J6: =H6-I6 | K6: =J6*(Assumptions!B15+Assumptions!B16) | L6: =J6-K6
A7: =Revenue!A7 | B7: =Revenue!G7 | C7: =B7*Assumptions!B4 | D7: =B7*Assumptions!B5 | E7: =B7*Assumptions!B6 | F7: =B7*Assumptions!B7 | G7: =Assumptions!B3 | H7: =B7-SUM(C7:G7) | I7: =Assumptions!B10/60 | J7: =H7-I7 | K7: =J7*(Assumptions!B15+Assumptions!B16) | L7: =J7-K7
A8: =Revenue!A8 | B8: =Revenue!G8 | C8: =B8*Assumptions!B4 | D8: =B8*Assumptions!B5 | E8: =B8*Assumptions!B6 | F8: =B8*Assumptions!B7 | G8: =Assumptions!B3 | H8: =B8-SUM(C8:G8) | I8: =Assumptions!B10/60 | J8: =H8-I8 | K8: =J8*(Assumptions!B15+Assumptions!B16) | L8: =J8-K8
A9: =Revenue!A9 | B9: =Revenue!G9 | C9: =B9*Assumptions!B4 | D9: =B9*Assumptions!B5 | E9: =B9*Assumptions!B6 | F9: =B9*Assumptions!B7 | G9: =Assumptions!B3 | H9: =B9-SUM(C9:G9) | I9: =Assumptions!B10/60 | J9: =H9-I9 | K9: =J9*(Assumptions!B15+Assumptions!B16) | L9: =J9-K9
A10: =Revenue!A10 | B10: =Revenue!G10 | C10: =B10*Assumptions!B4 | D10: =B10*Assumptions!B5 | E10: =B10*Assumptions!B6 | F10: =B10*Assumptions!B7 | G10: =Assumptions!B3 | H10: =B10-SUM(C10:G10) | I10: =Assumptions!B10/60 | J10: =H10-I10 | K10: =J10*(Assumptions!B15+Assumptions!B16) | L10: =J10-K10
A11: =Revenue!A11 | B11: =Revenue!G11 | C11: =B11*Assumptions!B4 | D11: =B11*Assumptions!B5 | E11: =B11*Assumptions!B6 | F11: =B11*Assumptions!B7 | G11: =Assumptions!B3 | H11: =B11-SUM(C11:G11) | I11: =Assumptions!B10/60 | J11: =H11-I11 | K11: =J11*(Assumptions!B15+Assumptions!B16) | L11: =J11-K11
A12: =Revenue!A12 | B12: =Revenue!G12 | C12: =B12*Assumptions!B4 | D12: =B12*Assumptions!B5 | E12: =B12*Assumptions!B6 | F12: =B12*Assumptions!B7 | G12: =Assumptions!B3 | H12: =B12-SUM(C12:G12) | I12: =Assumptions!B10/60 | J12: =H12-I12 | K12: =J12*(Assumptions!B15+Assumptions!B16) | L12: =J12-K12
A13: =Revenue!A13 | B13: =Revenue!G13 | C13: =B13*Assumptions!B4 | D13: =B13*Assumptions!B5 | E13: =B13*Assumptions!B6 | F13: =B13*Assumptions!B7 | G13: =Assumptions!B3 | H13: =B13-SUM(C13:G13) | I13: =Assumptions!B10/60 | J13: =H13-I13 | K13: =J13*(Assumptions!B15+Assumptions!B16) | L13: =J13-K13
A14: =Revenue!A14 | B14: =Revenue!G14 | C14: =B14*Assumptions!B4 | D14: =B14*Assumptions!B5 | E14: =B14*Assumptions!B6 | F14: =B14*Assumptions!B7 | G14: =Assumptions!B3 | H14: =B14-SUM(C14:G14) | I14: =Assumptions!B10/60 | J14: =H14-I14 | K14: =J14*(Assumptions!B15+Assumptions!B16) | L14: =J14-K14
A15: =Revenue!A15 | B15: =Revenue!G15 | C15: =B15*Assumptions!B4 | D15: =B15*Assumptions!B5 | E15: =B15*Assumptions!B6 | F15: =B15*Assumptions!B7 | G15: =Assumptions!B3 | H15: =B15-SUM(C15:G15) | I15: =Assumptions!B10/60 | J15: =H15-I15 | K15: =J15*(Assumptions!B15+Assumptions!B16) | L15: =J15-K15
A16: =Revenue!A16 | B16: =Revenue!G16 | C16: =B16*Assumptions!B4 | D16: =B16*Assumptions!B5 | E16: =B16*Assumptions!B6 | F16: =B16*Assumptions!B7 | G16: =Assumptions!B3 | H16: =B16-SUM(C16:G16) | I16: =Assumptions!B10/60 | J16: =H16-I16 | K16: =J16*(Assumptions!B15+Assumptions!B16) | L16: =J16-K16
A17: =Revenue!A17 | B17: =Revenue!G17 | C17: =B17*Assumptions!B4 | D17: =B17*Assumptions!B5 | E17: =B17*Assumptions!B6 | F17: =B17*Assumptions!B7 | G17: =Assumptions!B3 | H17: =B17-SUM(C17:G17) | I17: =Assumptions!B10/60 | J17: =H17-I17 | K17: =J17*(Assumptions!B15+Assumptions!B16) | L17: =J17-K17
A18: =Revenue!A18 | B18: =Revenue!G18 | C18: =B18*Assumptions!B4 | D18: =B18*Assumptions!B5 | E18: =B18*Assumptions!B6 | F18: =B18*Assumptions!B7 | G18: =Assumptions!B3 | H18: =B18-SUM(C18:G18) | I18: =Assumptions!B10/60 | J18: =H18-I18 | K18: =J18*(Assumptions!B15+Assumptions!B16) | L18: =J18-K18
A19: =Revenue!A19 | B19: =Revenue!G19 | C19: =B19*Assumptions!B4 | D19: =B19*Assumptions!B5 | E19: =B19*Assumptions!B6 | F19: =B19*Assumptions!B7 | G19: =Assumptions!B3 | H19: =B19-SUM(C19:G19) | I19: =Assumptions!B10/60 | J19: =H19-I19 | K19: =J19*(Assumptions!B15+Assumptions!B16) | L19: =J19-K19
A20: =Revenue!A20 | B20: =Revenue!G20 | C20: =B20*Assumptions!B4 | D20: =B20*Assumptions!B5 | E20: =B20*Assumptions!B6 | F20: =B20*Assumptions!B7 | G20: =Assumptions!B3 | H20: =B20-SUM(C20:G20) | I20: =Assumptions!B10/60 | J20: =H20-I20 | K20: =J20*(Assumptions!B15+Assumptions!B16) | L20: =J20-K20
A21: =Revenue!A21 | B21: =Revenue!G21 | C21: =B21*Assumptions!B4 | D21: =B21*Assumptions!B5 | E21: =B21*Assumptions!B6 | F21: =B21*Assumptions!B7 | G21: =Assumptions!B3 | H21: =B21-SUM(C21:G21) | I21: =Assumptions!B10/60 | J21: =H21-I21 | K21: =J21*(Assumptions!B15+Assumptions!B16) | L21: =J21-K21
A22: =Revenue!A22 | B22: =Revenue!G22 | C22: =B22*Assumptions!B4 | D22: =B22*Assumptions!B5 | E22: =B22*Assumptions!B6 | F22: =B22*Assumptions!B7 | G22: =Assumptions!B3 | H22: =B22-SUM(C22:G22) | I22: =Assumptions!B10/60 | J22: =H22-I22 | K22: =J22*(Assumptions!B15+Assumptions!B16) | L22: =J22-K22
A23: =Revenue!A23 | B23: =Revenue!G23 | C23: =B23*Assumptions!B4 | D23: =B23*Assumptions!B5 | E23: =B23*Assumptions!B6 | F23: =B23*Assumptions!B7 | G23: =Assumptions!B3 | H23: =B23-SUM(C23:G23) | I23: =Assumptions!B10/60 | J23: =H23-I23 | K23: =J23*(Assumptions!B15+Assumptions!B16) | L23: =J23-K23
A24: =Revenue!A24 | B24: =Revenue!G24 | C24: =B24*Assumptions!B4 | D24: =B24*Assumptions!B5 | E24: =B24*Assumptions!B6 | F24: =B24*Assumptions!B7 | G24: =Assumptions!B3 | H24: =B24-SUM(C24:G24) | I24: =Assumptions!B10/60 | J24: =H24-I24 | K24: =J24*(Assumptions!B15+Assumptions!B16) | L24: =J24-K24
A25: =Revenue!A25 | B25: =Revenue!G25 | C25: =B25*Assumptions!B4 | D25: =B25*Assumptions!B5 | E25: =B25*Assumptions!B6 | F25: =B25*Assumptions!B7 | G25: =Assumptions!B3 | H25: =B25-SUM(C25:G25) | I25: =Assumptions!B10/60 | J25: =H25-I25 | K25: =J25*(Assumptions!B15+Assumptions!B16) | L25: =J25-K25
A26: =Revenue!A26 | B26: =Revenue!G26 | C26: =B26*Assumptions!B4 | D26: =B26*Assumptions!B5 | E26: =B26*Assumptions!B6 | F26: =B26*Assumptions!B7 | G26: =Assumptions!B3 | H26: =B26-SUM(C26:G26) | I26: =Assumptions!B10/60 | J26: =H26-I26 | K26: =J26*(Assumptions!B15+Assumptions!B16) | L26: =J26-K26
A27: =Revenue!A27 | B27: =Revenue!G27 | C27: =B27*Assumptions!B4 | D27: =B27*Assumptions!B5 | E27: =B27*Assumptions!B6 | F27: =B27*Assumptions!B7 | G27: =Assumptions!B3 | H27: =B27-SUM(C27:G27) | I27: =Assumptions!B10/60 | J27: =H27-I27 | K27: =J27*(Assumptions!B15+Assumptions!B16) | L27: =J27-K27
A28: =Revenue!A28 | B28: =Revenue!G28 | C28: =B28*Assumptions!B4 | D28: =B28*Assumptions!B5 | E28: =B28*Assumptions!B6 | F28: =B28*Assumptions!B7 | G28: =Assumptions!B3 | H28: =B28-SUM(C28:G28) | I28: =Assumptions!B10/60 | J28: =H28-I28 | K28: =J28*(Assumptions!B15+Assumptions!B16) | L28: =J28-K28
A29: =Revenue!A29 | B29: =Revenue!G29 | C29: =B29*Assumptions!B4 | D29: =B29*Assumptions!B5 | E29: =B29*Assumptions!B6 | F29: =B29*Assumptions!B7 | G29: =Assumptions!B3 | H29: =B29-SUM(C29:G29) | I29: =Assumptions!B10/60 | J29: =H29-I29 | K29: =J29*(Assumptions!B15+Assumptions!B16) | L29: =J29-K29
A30: =Revenue!A30 | B30: =Revenue!G30 | C30: =B30*Assumptions!B4 | D30: =B30*Assumptions!B5 | E30: =B30*Assumptions!B6 | F30: =B30*Assumptions!B7 | G30: =Assumptions!B3 | H30: =B30-SUM(C30:G30) | I30: =Assumptions!B10/60 | J30: =H30-I30 | K30: =J30*(Assumptions!B15+Assumptions!B16) | L30: =J30-K30
A31: =Revenue!A31 | B31: =Revenue!G31 | C31: =B31*Assumptions!B4 | D31: =B31*Assumptions!B5 | E31: =B31*Assumptions!B6 | F31: =B31*Assumptions!B7 | G31: =Assumptions!B3 | H31: =B31-SUM(C31:G31) | I31: =Assumptions!B10/60 | J31: =H31-I31 | K31: =J31*(Assumptions!B15+Assumptions!B16) | L31: =J31-K31
A32: =Revenue!A32 | B32: =Revenue!G32 | C32: =B32*Assumptions!B4 | D32: =B32*Assumptions!B5 | E32: =B32*Assumptions!B6 | F32: =B32*Assumptions!B7 | G32: =Assumptions!B3 | H32: =B32-SUM(C32:G32) | I32: =Assumptions!B10/60 | J32: =H32-I32 | K32: =J32*(Assumptions!B15+Assumptions!B16) | L32: =J32-K32
A33: =Revenue!A33 | B33: =Revenue!G33 | C33: =B33*Assumptions!B4 | D33: =B33*Assumptions!B5 | E33: =B33*Assumptions!B6 | F33: =B33*Assumptions!B7 | G33: =Assumptions!B3 | H33: =B33-SUM(C33:G33) | I33: =Assumptions!B10/60 | J33: =H33-I33 | K33: =J33*(Assumptions!B15+Assumptions!B16) | L33: =J33-K33
A34: =Revenue!A34 | B34: =Revenue!G34 | C34: =B34*Assumptions!B4 | D34: =B34*Assumptions!B5 | E34: =B34*Assumptions!B6 | F34: =B34*Assumptions!B7 | G34: =Assumptions!B3 | H34: =B34-SUM(C34:G34) | I34: =Assumptions!B10/60 | J34: =H34-I34 | K34: =J34*(Assumptions!B15+Assumptions!B16) | L34: =J34-K34
A35: =Revenue!A35 | B35: =Revenue!G35 | C35: =B35*Assumptions!B4 | D35: =B35*Assumptions!B5 | E35: =B35*Assumptions!B6 | F35: =B35*Assumptions!B7 | G35: =Assumptions!B3 | H35: =B35-SUM(C35:G35) | I35: =Assumptions!B10/60 | J35: =H35-I35 | K35: =J35*(Assumptions!B15+Assumptions!B16) | L35: =J35-K35
A36: =Revenue!A36 | B36: =Revenue!G36 | C36: =B36*Assumptions!B4 | D36: =B36*Assumptions!B5 | E36: =B36*Assumptions!B6 | F36: =B36*Assumptions!B7 | G36: =Assumptions!B3 | H36: =B36-SUM(C36:G36) | I36: =Assumptions!B10/60 | J36: =H36-I36 | K36: =J36*(Assumptions!B15+Assumptions!B16) | L36: =J36-K36
A37: =Revenue!A37 | B37: =Revenue!G37 | C37: =B37*Assumptions!B4 | D37: =B37*Assumptions!B5 | E37: =B37*Assumptions!B6 | F37: =B37*Assumptions!B7 | G37: =Assumptions!B3 | H37: =B37-SUM(C37:G37) | I37: =Assumptions!B10/60 | J37: =H37-I37 | K37: =J37*(Assumptions!B15+Assumptions!B16) | L37: =J37-K37
A38: =Revenue!A38 | B38: =Revenue!G38 | C38: =B38*Assumptions!B4 | D38: =B38*Assumptions!B5 | E38: =B38*Assumptions!B6 | F38: =B38*Assumptions!B7 | G38: =Assumptions!B3 | H38: =B38-SUM(C38:G38) | I38: =Assumptions!B10/60 | J38: =H38-I38 | K38: =J38*(Assumptions!B15+Assumptions!B16) | L38: =J38-K38
A39: =Revenue!A39 | B39: =Revenue!G39 | C39: =B39*Assumptions!B4 | D39: =B39*Assumptions!B5 | E39: =B39*Assumptions!B6 | F39: =B39*Assumptions!B7 | G39: =Assumptions!B3 | H39: =B39-SUM(C39:G39) | I39: =Assumptions!B10/60 | J39: =H39-I39 | K39: =J39*(Assumptions!B15+Assumptions!B16) | L39: =J39-K39
A40: =Revenue!A40 | B40: =Revenue!G40 | C40: =B40*Assumptions!B4 | D40: =B40*Assumptions!B5 | E40: =B40*Assumptions!B6 | F40: =B40*Assumptions!B7 | G40: =Assumptions!B3 | H40: =B40-SUM(C40:G40) | I40: =Assumptions!B10/60 | J40: =H40-I40 | K40: =J40*(Assumptions!B15+Assumptions!B16) | L40: =J40-K40
A41: =Revenue!A41 | B41: =Revenue!G41 | C41: =B41*Assumptions!B4 | D41: =B41*Assumptions!B5 | E41: =B41*Assumptions!B6 | F41: =B41*Assumptions!B7 | G41: =Assumptions!B3 | H41: =B41-SUM(C41:G41) | I41: =Assumptions!B10/60 | J41: =H41-I41 | K41: =J41*(Assumptions!B15+Assumptions!B16) | L41: =J41-K41
A42: =Revenue!A42 | B42: =Revenue!G42 | C42: =B42*Assumptions!B4 | D42: =B42*Assumptions!B5 | E42: =B42*Assumptions!B6 | F42: =B42*Assumptions!B7 | G42: =Assumptions!B3 | H42: =B42-SUM(C42:G42) | I42: =Assumptions!B10/60 | J42: =H42-I42 | K42: =J42*(Assumptions!B15+Assumptions!B16) | L42: =J42-K42
A43: =Revenue!A43 | B43: =Revenue!G43 | C43: =B43*Assumptions!B4 | D43: =B43*Assumptions!B5 | E43: =B43*Assumptions!B6 | F43: =B43*Assumptions!B7 | G43: =Assumptions!B3 | H43: =B43-SUM(C43:G43) | I43: =Assumptions!B10/60 | J43: =H43-I43 | K43: =J43*(Assumptions!B15+Assumptions!B16) | L43: =J43-K43
A44: =Revenue!A44 | B44: =Revenue!G44 | C44: =B44*Assumptions!B4 | D44: =B44*Assumptions!B5 | E44: =B44*Assumptions!B6 | F44: =B44*Assumptions!B7 | G44: =Assumptions!B3 | H44: =B44-SUM(C44:G44) | I44: =Assumptions!B10/60 | J44: =H44-I44 | K44: =J44*(Assumptions!B15+Assumptions!B16) | L44: =J44-K44
A45: =Revenue!A45 | B45: =Revenue!G45 | C45: =B45*Assumptions!B4 | D45: =B45*Assumptions!B5 | E45: =B45*Assumptions!B6 | F45: =B45*Assumptions!B7 | G45: =Assumptions!B3 | H45: =B45-SUM(C45:G45) | I45: =Assumptions!B10/60 | J45: =H45-I45 | K45: =J45*(Assumptions!B15+Assumptions!B16) | L45: =J45-K45
A46: =Revenue!A46 | B46: =Revenue!G46 | C46: =B46*Assumptions!B4 | D46: =B46*Assumptions!B5 | E46: =B46*Assumptions!B6 | F46: =B46*Assumptions!B7 | G46: =Assumptions!B3 | H46: =B46-SUM(C46:G46) | I46: =Assumptions!B10/60 | J46: =H46-I46 | K46: =J46*(Assumptions!B15+Assumptions!B16) | L46: =J46-K46
A47: =Revenue!A47 | B47: =Revenue!G47 | C47: =B47*Assumptions!B4 | D47: =B47*Assumptions!B5 | E47: =B47*Assumptions!B6 | F47: =B47*Assumptions!B7 | G47: =Assumptions!B3 | H47: =B47-SUM(C47:G47) | I47: =Assumptions!B10/60 | J47: =H47-I47 | K47: =J47*(Assumptions!B15+Assumptions!B16) | L47: =J47-K47
A48: =Revenue!A48 | B48: =Revenue!G48 | C48: =B48*Assumptions!B4 | D48: =B48*Assumptions!B5 | E48: =B48*Assumptions!B6 | F48: =B48*Assumptions!B7 | G48: =Assumptions!B3 | H48: =B48-SUM(C48:G48) | I48: =Assumptions!B10/60 | J48: =H48-I48 | K48: =J48*(Assumptions!B15+Assumptions!B16) | L48: =J48-K48
A49: =Revenue!A49 | B49: =Revenue!G49 | C49: =B49*Assumptions!B4 | D49: =B49*Assumptions!B5 | E49: =B49*Assumptions!B6 | F49: =B49*Assumptions!B7 | G49: =Assumptions!B3 | H49: =B49-SUM(C49:G49) | I49: =Assumptions!B10/60 | J49: =H49-I49 | K49: =J49*(Assumptions!B15+Assumptions!B16) | L49: =J49-K49
A50: =Revenue!A50 | B50: =Revenue!G50 | C50: =B50*Assumptions!B4 | D50: =B50*Assumptions!B5 | E50: =B50*Assumptions!B6 | F50: =B50*Assumptions!B7 | G50: =Assumptions!B3 | H50: =B50-SUM(C50:G50) | I50: =Assumptions!B10/60 | J50: =H50-I50 | K50: =J50*(Assumptions!B15+Assumptions!B16) | L50: =J50-K50
A51: =Revenue!A51 | B51: =Revenue!G51 | C51: =B51*Assumptions!B4 | D51: =B51*Assumptions!B5 | E51: =B51*Assumptions!B6 | F51: =B51*Assumptions!B7 | G51: =Assumptions!B3 | H51: =B51-SUM(C51:G51) | I51: =Assumptions!B10/60 | J51: =H51-I51 | K51: =J51*(Assumptions!B15+Assumptions!B16) | L51: =J51-K51
A52: =Revenue!A52 | B52: =Revenue!G52 | C52: =B52*Assumptions!B4 | D52: =B52*Assumptions!B5 | E52: =B52*Assumptions!B6 | F52: =B52*Assumptions!B7 | G52: =Assumptions!B3 | H52: =B52-SUM(C52:G52) | I52: =Assumptions!B10/60 | J52: =H52-I52 | K52: =J52*(Assumptions!B15+Assumptions!B16) | L52: =J52-K52
A53: =Revenue!A53 | B53: =Revenue!G53 | C53: =B53*Assumptions!B4 | D53: =B53*Assumptions!B5 | E53: =B53*Assumptions!B6 | F53: =B53*Assumptions!B7 | G53: =Assumptions!B3 | H53: =B53-SUM(C53:G53) | I53: =Assumptions!B10/60 | J53: =H53-I53 | K53: =J53*(Assumptions!B15+Assumptions!B16) | L53: =J53-K53
A54: =Revenue!A54 | B54: =Revenue!G54 | C54: =B54*Assumptions!B4 | D54: =B54*Assumptions!B5 | E54: =B54*Assumptions!B6 | F54: =B54*Assumptions!B7 | G54: =Assumptions!B3 | H54: =B54-SUM(C54:G54) | I54: =Assumptions!B10/60 | J54: =H54-I54 | K54: =J54*(Assumptions!B15+Assumptions!B16) | L54: =J54-K54
A55: =Revenue!A55 | B55: =Revenue!G55 | C55: =B55*Assumptions!B4 | D55: =B55*Assumptions!B5 | E55: =B55*Assumptions!B6 | F55: =B55*Assumptions!B7 | G55: =Assumptions!B3 | H55: =B55-SUM(C55:G55) | I55: =Assumptions!B10/60 | J55: =H55-I55 | K55: =J55*(Assumptions!B15+Assumptions!B16) | L55: =J55-K55
A56: =Revenue!A56 | B56: =Revenue!G56 | C56: =B56*Assumptions!B4 | D56: =B56*Assumptions!B5 | E56: =B56*Assumptions!B6 | F56: =B56*Assumptions!B7 | G56: =Assumptions!B3 | H56: =B56-SUM(C56:G56) | I56: =Assumptions!B10/60 | J56: =H56-I56 | K56: =J56*(Assumptions!B15+Assumptions!B16) | L56: =J56-K56
A57: =Revenue!A57 | B57: =Revenue!G57 | C57: =B57*Assumptions!B4 | D57: =B57*Assumptions!B5 | E57: =B57*Assumptions!B6 | F57: =B57*Assumptions!B7 | G57: =Assumptions!B3 | H57: =B57-SUM(C57:G57) | I57: =Assumptions!B10/60 | J57: =H57-I57 | K57: =J57*(Assumptions!B15+Assumptions!B16) | L57: =J57-K57
A58: =Revenue!A58 | B58: =Revenue!G58 | C58: =B58*Assumptions!B4 | D58: =B58*Assumptions!B5 | E58: =B58*Assumptions!B6 | F58: =B58*Assumptions!B7 | G58: =Assumptions!B3 | H58: =B58-SUM(C58:G58) | I58: =Assumptions!B10/60 | J58: =H58-I58 | K58: =J58*(Assumptions!B15+Assumptions!B16) | L58: =J58-K58
A59: =Revenue!A59 | B59: =Revenue!G59 | C59: =B59*Assumptions!B4 | D59: =B59*Assumptions!B5 | E59: =B59*Assumptions!B6 | F59: =B59*Assumptions!B7 | G59: =Assumptions!B3 | H59: =B59-SUM(C59:G59) | I59: =Assumptions!B10/60 | J59: =H59-I59 | K59: =J59*(Assumptions!B15+Assumptions!B16) | L59: =J59-K59
A60: =Revenue!A60 | B60: =Revenue!G60 | C60: =B60*Assumptions!B4 | D60: =B60*Assumptions!B5 | E60: =B60*Assumptions!B6 | F60: =B60*Assumptions!B7 | G60: =Assumptions!B3 | H60: =B60-SUM(C60:G60) | I60: =Assumptions!B10/60 | J60: =H60-I60 | K60: =J60*(Assumptions!B15+Assumptions!B16) | L60: =J60-K60
A61: =Revenue!A61 | B61: =Revenue!G61 | C61: =B61*Assumptions!B4 | D61: =B61*Assumptions!B5 | E61: =B61*Assumptions!B6 | F61: =B61*Assumptions!B7 | G61: =Assumptions!B3 | H61: =B61-SUM(C61:G61) | I61: =Assumptions!B10/60 | J61: =H61-I61 | K61: =J61*(Assumptions!B15+Assumptions!B16) | L61: =J61-K61
A63: Year 2024 | B63: =SUM(B2:B13) | C63: =SUM(C2:C13) | D63: =SUM(D2:D13) | E63: =SUM(E2:E13) | F63: =SUM(F2:F13) | G63: =SUM(G2:G13) | H63: =SUM(H2:H13) | I63: =SUM(I2:I13) | ... L63: =SUM(L2:L13)
A64: Year 2025 | B64: =SUM(B14:B25) | C64: =SUM(C14:C25) | D64: =SUM(D14:D25) | E64: =SUM(E14:E25) | F64: =SUM(F14:F25) | G64: =SUM(G14:G25) | H64: =SUM(H14:H25) | I64: =SUM(I14:I25) | ... L64: =SUM(L14:L25)
A65: Year 2026 | B65: =SUM(B26:B37) | C65: =SUM(C26:C37) | D65: =SUM(D26:D37) | E65: =SUM(E26:E37) | F65: =SUM(F26:F37) | G65: =SUM(G26:G37) | H65: =SUM(H26:H37) | I65: =SUM(I26:I37) | ... L65: =SUM(L26:L37)
A66: Year 2027 | B66: =SUM(B38:B49) | C66: =SUM(C38:C49) | D66: =SUM(D38:D49) | E66: =SUM(E38:E49) | F66: =SUM(F38:F49) | G66: =SUM(G38:G49) | H66: =SUM(H38:H49) | I66: =SUM(I38:I49) | ... L66: =SUM(L38:L49)
A67: Year 2028 | B67: =SUM(B50:B61) | C67: =SUM(C50:C61) | D67: =SUM(D50:D61) | E67: =SUM(E50:E61) | F67: =SUM(F50:F61) | G67: =SUM(G50:G61) | H67: =SUM(H50:H61) | I67: =SUM(I50:I61) | ... L67: =SUM(L50:L61)

Sheet CashFlow
A1: Year | B1: EBITDA | C1: Taxes | D1: Delta NWC | E1: Operating CF | F1: Capex Initial | G1: Maintenance Capex | H1: Investing CF | I1: Financing CF | J1: FCF | K1: Cumulative FCF
A2: 2024 | B2: =PnL!H63 | C2: =PnL!K63 | D2: =0.1*PnL!B63 | E2: =B2-C2-D2 | F2: =Assumptions!B10 | G2: =Assumptions!B10*0.02 | H2: =-F2-G2 | I2: 0 | J2: =E2+H2+I2 | K2: =IF(A2=2024,J2,J2+K1)
A3: 2025 | B3: =PnL!H64 | C3: =PnL!K64 | D3: =0.1*(PnL!B64-PnL!B63) | E3: =B3-C3-D3 | F3: =0 | G3: =Assumptions!B10*0.02 | H3: =-F3-G3 | I3: 0 | J3: =E3+H3+I3 | K3: =IF(A3=2024,J3,J3+K2)
A4: 2026 | B4: =PnL!H65 | C4: =PnL!K65 | D4: =0.1*(PnL!B65-PnL!B64) | E4: =B4-C4-D4 | F4: =0 | G4: =Assumptions!B10*0.02 | H4: =-F4-G4 | I4: 0 | J4: =E4+H4+I4 | K4: =IF(A4=2024,J4,J4+K3)
A5: 2027 | B5: =PnL!H66 | C5: =PnL!K66 | D5: =0.1*(PnL!B66-PnL!B65) | E5: =B5-C5-D5 | F5: =0 | G5: =Assumptions!B10*0.02 | H5: =-F5-G5 | I5: 0 | J5: =E5+H5+I5 | K5: =IF(A5=2024,J5,J5+K4)
A6: 2028 | B6: =PnL!H67 | C6: =PnL!K67 | D6: =0.1*(PnL!B67-PnL!B66) | E6: =B6-C6-D6 | F6: =0 | G6: =Assumptions!B10*0.02 | H6: =-F6-G6 | I6: 0 | J6: =E6+H6+I6 | K6: =IF(A6=2024,J6,J6+K5)

Sheet BreakEven
A1: Month | B1: Revenue | C1: Fixed Costs | D1: Variable Costs | E1: Contribution Margin | F1: Break-Even Revenue
A2: =Revenue!A2 | B2: =Revenue!G2 | C2: =Assumptions!B3+Personnel!D5+Assumptions!B10/60 | D2: =B2*(Assumptions!B4+Assumptions!B5+Assumptions!B6+Assumptions!B7) | E2: =B2-D2 | F2: =IF(B2=0,0,C2/(E2/B2))
A3: =Revenue!A3 | B3: =Revenue!G3 | C3: =Assumptions!B3+Personnel!D5+Assumptions!B10/60 | D3: =B3*(Assumptions!B4+Assumptions!B5+Assumptions!B6+Assumptions!B7) | E3: =B3-D3 | F3: =IF(B3=0,0,C3/(E3/B3))
A4: =Revenue!A4 | B4: =Revenue!G4 | C4: =Assumptions!B3+Personnel!D5+Assumptions!B10/60 | D4: =B4*(Assumptions!B4+Assumptions!B5+Assumptions!B6+Assumptions!B7) | E4: =B4-D4 | F4: =IF(B4=0,0,C4/(E4/B4))
A5: =Revenue!A5 | B5: =Revenue!G5 | C5: =Assumptions!B3+Personnel!D5+Assumptions!B10/60 | D5: =B5*(Assumptions!B4+Assumptions!B5+Assumptions!B6+Assumptions!B7) | E5: =B5-D5 | F5: =IF(B5=0,0,C5/(E5/B5))
A6: =Revenue!A6 | B6: =Revenue!G6 | C6: =Assumptions!B3+Personnel!D5+Assumptions!B10/60 | D6: =B6*(Assumptions!B4+Assumptions!B5+Assumptions!B6+Assumptions!B7) | E6: =B6-D6 | F6: =IF(B6=0,0,C6/(E6/B6))
A7: =Revenue!A7 | B7: =Revenue!G7 | C7: =Assumptions!B3+Personnel!D5+Assumptions!B10/60 | D7: =B7*(Assumptions!B4+Assumptions!B5+Assumptions!B6+Assumptions!B7) | E7: =B7-D7 | F7: =IF(B7=0,0,C7/(E7/B7))
A8: =Revenue!A8 | B8: =Revenue!G8 | C8: =Assumptions!B3+Personnel!D5+Assumptions!B10/60 | D8: =B8*(Assumptions!B4+Assumptions!B5+Assumptions!B6+Assumptions!B7) | E8: =B8-D8 | F8: =IF(B8=0,0,C8/(E8/B8))
A9: =Revenue!A9 | B9: =Revenue!G9 | C9: =Assumptions!B3+Personnel!D5+Assumptions!B10/60 | D9: =B9*(Assumptions!B4+Assumptions!B5+Assumptions!B6+Assumptions!B7) | E9: =B9-D9 | F9: =IF(B9=0,0,C9/(E9/B9))
A10: =Revenue!A10 | B10: =Revenue!G10 | C10: =Assumptions!B3+Personnel!D5+Assumptions!B10/60 | D10: =B10*(Assumptions!B4+Assumptions!B5+Assumptions!B6+Assumptions!B7) | E10: =B10-D10 | F10: =IF(B10=0,0,C10/(E10/B10))
A11: =Revenue!A11 | B11: =Revenue!G11 | C11: =Assumptions!B3+Personnel!D5+Assumptions!B10/60 | D11: =B11*(Assumptions!B4+Assumptions!B5+Assumptions!B6+Assumptions!B7) | E11: =B11-D11 | F11: =IF(B11=0,0,C11/(E11/B11))
A12: =Revenue!A12 | B12: =Revenue!G12 | C12: =Assumptions!B3+Personnel!D5+Assumptions!B10/60 | D12: =B12*(Assumptions!B4+Assumptions!B5+Assumptions!B6+Assumptions!B7) | E12: =B12-D12 | F12: =IF(B12=0,0,C12/(E12/B12))
A13: =Revenue!A13 | B13: =Revenue!G13 | C13: =Assumptions!B3+Personnel!D5+Assumptions!B10/60 | D13: =B13*(Assumptions!B4+Assumptions!B5+Assumptions!B6+Assumptions!B7) | E13: =B13-D13 | F13: =IF(B13=0,0,C13/(E13/B13))
A14: =Revenue!A14 | B14: =Revenue!G14 | C14: =Assumptions!B3+Personnel!D5+Assumptions!B10/60 | D14: =B14*(Assumptions!B4+Assumptions!B5+Assumptions!B6+Assumptions!B7) | E14: =B14-D14 | F14: =IF(B14=0,0,C14/(E14/B14))
A15: =Revenue!A15 | B15: =Revenue!G15 | C15: =Assumptions!B3+Personnel!D5+Assumptions!B10/60 | D15: =B15*(Assumptions!B4+Assumptions!B5+Assumptions!B6+Assumptions!B7) | E15: =B15-D15 | F15: =IF(B15=0,0,C15/(E15/B15))
A16: =Revenue!A16 | B16: =Revenue!G16 | C16: =Assumptions!B3+Personnel!D5+Assumptions!B10/60 | D16: =B16*(Assumptions!B4+Assumptions!B5+Assumptions!B6+Assumptions!B7) | E16: =B16-D16 | F16: =IF(B16=0,0,C16/(E16/B16))
A17: =Revenue!A17 | B17: =Revenue!G17 | C17: =Assumptions!B3+Personnel!D5+Assumptions!B10/60 | D17: =B17*(Assumptions!B4+Assumptions!B5+Assumptions!B6+Assumptions!B7) | E17: =B17-D17 | F17: =IF(B17=0,0,C17/(E17/B17))
A18: =Revenue!A18 | B18: =Revenue!G18 | C18: =Assumptions!B3+Personnel!D5+Assumptions!B10/60 | D18: =B18*(Assumptions!B4+Assumptions!B5+Assumptions!B6+Assumptions!B7) | E18: =B18-D18 | F18: =IF(B18=0,0,C18/(E18/B18))
A19: =Revenue!A19 | B19: =Revenue!G19 | C19: =Assumptions!B3+Personnel!D5+Assumptions!B10/60 | D19: =B19*(Assumptions!B4+Assumptions!B5+Assumptions!B6+Assumptions!B7) | E19: =B19-D19 | F19: =IF(B19=0,0,C19/(E19/B19))
A20: =Revenue!A20 | B20: =Revenue!G20 | C20: =Assumptions!B3+Personnel!D5+Assumptions!B10/60 | D20: =B20*(Assumptions!B4+Assumptions!B5+Assumptions!B6+Assumptions!B7) | E20: =B20-D20 | F20: =IF(B20=0,0,C20/(E20/B20))
A21: =Revenue!A21 | B21: =Revenue!G21 | C21: =Assumptions!B3+Personnel!D5+Assumptions!B10/60 | D21: =B21*(Assumptions!B4+Assumptions!B5+Assumptions!B6+Assumptions!B7) | E21: =B21-D21 | F21: =IF(B21=0,0,C21/(E21/B21))
A22: =Revenue!A22 | B22: =Revenue!G22 | C22: =Assumptions!B3+Personnel!D5+Assumptions!B10/60 | D22: =B22*(Assumptions!B4+Assumptions!B5+Assumptions!B6+Assumptions!B7) | E22: =B22-D22 | F22: =IF(B22=0,0,C22/(E22/B22))
A23: =Revenue!A23 | B23: =Revenue!G23 | C23: =Assumptions!B3+Personnel!D5+Assumptions!B10/60 | D23: =B23*(Assumptions!B4+Assumptions!B5+Assumptions!B6+Assumptions!B7) | E23: =B23-D23 | F23: =IF(B23=0,0,C23/(E23/B23))
A24: =Revenue!A24 | B24: =Revenue!G24 | C24: =Assumptions!B3+Personnel!D5+Assumptions!B10/60 | D24: =B24*(Assumptions!B4+Assumptions!B5+Assumptions!B6+Assumptions!B7) | E24: =B24-D24 | F24: =IF(B24=0,0,C24/(E24/B24))
A25: =Revenue!A25 | B25: =Revenue!G25 | C25: =Assumptions!B3+Personnel!D5+Assumptions!B10/60 | D25: =B25*(Assumptions!B4+Assumptions!B5+Assumptions!B6+Assumptions!B7) | E25: =B25-D25 | F25: =IF(B25=0,0,C25/(E25/B25))
A26: =Revenue!A26 | B26: =Revenue!G26 | C26: =Assumptions!B3+Personnel!D5+Assumptions!B10/60 | D26: =B26*(Assumptions!B4+Assumptions!B5+Assumptions!B6+Assumptions!B7) | E26: =B26-D26 | F26: =IF(B26=0,0,C26/(E26/B26))
A27: =Revenue!A27 | B27: =Revenue!G27 | C27: =Assumptions!B3+Personnel!D5+Assumptions!B10/60 | D27: =B27*(Assumptions!B4+Assumptions!B5+Assumptions!B6+Assumptions!B7) | E27: =B27-D27 | F27: =IF(B27=0,0,C27/(E27/B27))
A28: =Revenue!A28 | B28: =Revenue!G28 | C28: =Assumptions!B3+Personnel!D5+Assumptions!B10/60 | D28: =B28*(Assumptions!B4+Assumptions!B5+Assumptions!B6+Assumptions!B7) | E28: =B28-D28 | F28: =IF(B28=0,0,C28/(E28/B28))
A29: =Revenue!A29 | B29: =Revenue!G29 | C29: =Assumptions!B3+Personnel!D5+Assumptions!B10/60 | D29: =B29*(Assumptions!B4+Assumptions!B5+Assumptions!B6+Assumptions!B7) | E29: =B29-D29 | F29: =IF(B29=0,0,C29/(E29/B29))
A30: =Revenue!A30 | B30: =Revenue!G30 | C30: =Assumptions!B3+Personnel!D5+Assumptions!B10/60 | D30: =B30*(Assumptions!B4+Assumptions!B5+Assumptions!B6+Assumptions!B7) | E30: =B30-D30 | F30: =IF(B30=0,0,C30/(E30/B30))
A31: =Revenue!A31 | B31: =Revenue!G31 | C31: =Assumptions!B3+Personnel!D5+Assumptions!B10/60 | D31: =B31*(Assumptions!B4+Assumptions!B5+Assumptions!B6+Assumptions!B7) | E31: =B31-D31 | F31: =IF(B31=0,0,C31/(E31/B31))
A32: =Revenue!A32 | B32: =Revenue!G32 | C32: =Assumptions!B3+Personnel!D5+Assumptions!B10/60 | D32: =B32*(Assumptions!B4+Assumptions!B5+Assumptions!B6+Assumptions!B7) | E32: =B32-D32 | F32: =IF(B32=0,0,C32/(E32/B32))
A33: =Revenue!A33 | B33: =Revenue!G33 | C33: =Assumptions!B3+Personnel!D5+Assumptions!B10/60 | D33: =B33*(Assumptions!B4+Assumptions!B5+Assumptions!B6+Assumptions!B7) | E33: =B33-D33 | F33: =IF(B33=0,0,C33/(E33/B33))
A34: =Revenue!A34 | B34: =Revenue!G34 | C34: =Assumptions!B3+Personnel!D5+Assumptions!B10/60 | D34: =B34*(Assumptions!B4+Assumptions!B5+Assumptions!B6+Assumptions!B7) | E34: =B34-D34 | F34: =IF(B34=0,0,C34/(E34/B34))
A35: =Revenue!A35 | B35: =Revenue!G35 | C35: =Assumptions!B3+Personnel!D5+Assumptions!B10/60 | D35: =B35*(Assumptions!B4+Assumptions!B5+Assumptions!B6+Assumptions!B7) | E35: =B35-D35 | F35: =IF(B35=0,0,C35/(E35/B35))
A36: =Revenue!A36 | B36: =Revenue!G36 | C36: =Assumptions!B3+Personnel!D5+Assumptions!B10/60 | D36: =B36*(Assumptions!B4+Assumptions!B5+Assumptions!B6+Assumptions!B7) | E36: =B36-D36 | F36: =IF(B36=0,0,C36/(E36/B36))
A37: =Revenue!A37 | B37: =Revenue!G37 | C37: =Assumptions!B3+Personnel!D5+Assumptions!B10/60 | D37: =B37*(Assumptions!B4+Assumptions!B5+Assumptions!B6+Assumptions!B7) | E37: =B37-D37 | F37: =IF(B37=0,0,C37/(E37/B37))
A38: =Revenue!A38 | B38: =Revenue!G38 | C38: =Assumptions!B3+Personnel!D5+Assumptions!B10/60 | D38: =B38*(Assumptions!B4+Assumptions!B5+Assumptions!B6+Assumptions!B7) | E38: =B38-D38 | F38: =IF(B38=0,0,C38/(E38/B38))
A39: =Revenue!A39 | B39: =Revenue!G39 | C39: =Assumptions!B3+Personnel!D5+Assumptions!B10/60 | D39: =B39*(Assumptions!B4+Assumptions!B5+Assumptions!B6+Assumptions!B7) | E39: =B39-D39 | F39: =IF(B39=0,0,C39/(E39/B39))
A40: =Revenue!A40 | B40: =Revenue!G40 | C40: =Assumptions!B3+Personnel!D5+Assumptions!B10/60 | D40: =B40*(Assumptions!B4+Assumptions!B5+Assumptions!B6+Assumptions!B7) | E40: =B40-D40 | F40: =IF(B40=0,0,C40/(E40/B40))
A41: =Revenue!A41 | B41: =Revenue!G41 | C41: =Assumptions!B3+Personnel!D5+Assumptions!B10/60 | D41: =B41*(Assumptions!B4+Assumptions!B5+Assumptions!B6+Assumptions!B7) | E41: =B41-D41 | F41: =IF(B41=0,0,C41/(E41/B41))
A42: =Revenue!A42 | B42: =Revenue!G42 | C42: =Assumptions!B3+Personnel!D5+Assumptions!B10/60 | D42: =B42*(Assumptions!B4+Assumptions!B5+Assumptions!B6+Assumptions!B7) | E42: =B42-D42 | F42: =IF(B42=0,0,C42/(E42/B42))
A43: =Revenue!A43 | B43: =Revenue!G43 | C43: =Assumptions!B3+Personnel!D5+Assumptions!B10/60 | D43: =B43*(Assumptions!B4+Assumptions!B5+Assumptions!B6+Assumptions!B7) | E43: =B43-D43 | F43: =IF(B43=0,0,C43/(E43/B43))
A44: =Revenue!A44 | B44: =Revenue!G44 | C44: =Assumptions!B3+Personnel!D5+Assumptions!B10/60 | D44: =B44*(Assumptions!B4+Assumptions!B5+Assumptions!B6+Assumptions!B7) | E44: =B44-D44 | F44: =IF(B44=0,0,C44/(E44/B44))
A45: =Revenue!A45 | B45: =Revenue!G45 | C45: =Assumptions!B3+Personnel!D5+Assumptions!B10/60 | D45: =B45*(Assumptions!B4+Assumptions!B5+Assumptions!B6+Assumptions!B7) | E45: =B45-D45 | F45: =IF(B45=0,0,C45/(E45/B45))
A46: =Revenue!A46 | B46: =Revenue!G46 | C46: =Assumptions!B3+Personnel!D5+Assumptions!B10/60 | D46: =B46*(Assumptions!B4+Assumptions!B5+Assumptions!B6+Assumptions!B7) | E46: =B46-D46 | F46: =IF(B46=0,0,C46/(E46/B46))
A47: =Revenue!A47 | B47: =Revenue!G47 | C47: =Assumptions!B3+Personnel!D5+Assumptions!B10/60 | D47: =B47*(Assumptions!B4+Assumptions!B5+Assumptions!B6+Assumptions!B7) | E47: =B47-D47 | F47: =IF(B47=0,0,C47/(E47/B47))
A48: =Revenue!A48 | B48: =Revenue!G48 | C48: =Assumptions!B3+Personnel!D5+Assumptions!B10/60 | D48: =B48*(Assumptions!B4+Assumptions!B5+Assumptions!B6+Assumptions!B7) | E48: =B48-D48 | F48: =IF(B48=0,0,C48/(E48/B48))
A49: =Revenue!A49 | B49: =Revenue!G49 | C49: =Assumptions!B3+Personnel!D5+Assumptions!B10/60 | D49: =B49*(Assumptions!B4+Assumptions!B5+Assumptions!B6+Assumptions!B7) | E49: =B49-D49 | F49: =IF(B49=0,0,C49/(E49/B49))
A50: =Revenue!A50 | B50: =Revenue!G50 | C50: =Assumptions!B3+Personnel!D5+Assumptions!B10/60 | D50: =B50*(Assumptions!B4+Assumptions!B5+Assumptions!B6+Assumptions!B7) | E50: =B50-D50 | F50: =IF(B50=0,0,C50/(E50/B50))
A51: =Revenue!A51 | B51: =Revenue!G51 | C51: =Assumptions!B3+Personnel!D5+Assumptions!B10/60 | D51: =B51*(Assumptions!B4+Assumptions!B5+Assumptions!B6+Assumptions!B7) | E51: =B51-D51 | F51: =IF(B51=0,0,C51/(E51/B51))
A52: =Revenue!A52 | B52: =Revenue!G52 | C52: =Assumptions!B3+Personnel!D5+Assumptions!B10/60 | D52: =B52*(Assumptions!B4+Assumptions!B5+Assumptions!B6+Assumptions!B7) | E52: =B52-D52 | F52: =IF(B52=0,0,C52/(E52/B52))
A53: =Revenue!A53 | B53: =Revenue!G53 | C53: =Assumptions!B3+Personnel!D5+Assumptions!B10/60 | D53: =B53*(Assumptions!B4+Assumptions!B5+Assumptions!B6+Assumptions!B7) | E53: =B53-D53 | F53: =IF(B53=0,0,C53/(E53/B53))
A54: =Revenue!A54 | B54: =Revenue!G54 | C54: =Assumptions!B3+Personnel!D5+Assumptions!B10/60 | D54: =B54*(Assumptions!B4+Assumptions!B5+Assumptions!B6+Assumptions!B7) | E54: =B54-D54 | F54: =IF(B54=0,0,C54/(E54/B54))
A55: =Revenue!A55 | B55: =Revenue!G55 | C55: =Assumptions!B3+Personnel!D5+Assumptions!B10/60 | D55: =B55*(Assumptions!B4+Assumptions!B5+Assumptions!B6+Assumptions!B7) | E55: =B55-D55 | F55: =IF(B55=0,0,C55/(E55/B55))
A56: =Revenue!A56 | B56: =Revenue!G56 | C56: =Assumptions!B3+Personnel!D5+Assumptions!B10/60 | D56: =B56*(Assumptions!B4+Assumptions!B5+Assumptions!B6+Assumptions!B7) | E56: =B56-D56 | F56: =IF(B56=0,0,C56/(E56/B56))
A57: =Revenue!A57 | B57: =Revenue!G57 | C57: =Assumptions!B3+Personnel!D5+Assumptions!B10/60 | D57: =B57*(Assumptions!B4+Assumptions!B5+Assumptions!B6+Assumptions!B7) | E57: =B57-D57 | F57: =IF(B57=0,0,C57/(E57/B57))
A58: =Revenue!A58 | B58: =Revenue!G58 | C58: =Assumptions!B3+Personnel!D5+Assumptions!B10/60 | D58: =B58*(Assumptions!B4+Assumptions!B5+Assumptions!B6+Assumptions!B7) | E58: =B58-D58 | F58: =IF(B58=0,0,C58/(E58/B58))
A59: =Revenue!A59 | B59: =Revenue!G59 | C59: =Assumptions!B3+Personnel!D5+Assumptions!B10/60 | D59: =B59*(Assumptions!B4+Assumptions!B5+Assumptions!B6+Assumptions!B7) | E59: =B59-D59 | F59: =IF(B59=0,0,C59/(E59/B59))
A60: =Revenue!A60 | B60: =Revenue!G60 | C60: =Assumptions!B3+Personnel!D5+Assumptions!B10/60 | D60: =B60*(Assumptions!B4+Assumptions!B5+Assumptions!B6+Assumptions!B7) | E60: =B60-D60 | F60: =IF(B60=0,0,C60/(E60/B60))
A61: =Revenue!A61 | B61: =Revenue!G61 | C61: =Assumptions!B3+Personnel!D5+Assumptions!B10/60 | D61: =B61*(Assumptions!B4+Assumptions!B5+Assumptions!B6+Assumptions!B7) | E61: =B61-D61 | F61: =IF(B61=0,0,C61/(E61/B61))

Sheet ScaleUp
A1: Location | B1: Year Opened | C1: Capex | D1: Population | E1: Scale Factor | F1: 2024 Revenue | G1: 2025 Revenue | H1: 2026 Revenue | I1: 2027 Revenue | J1: 2028 Revenue
A2: Milano | B2: 2024 | C2: 350000 | D2: 1.4 | E2: 1 | F2: =PnL!B63*E2 | G2: =PnL!B64*E2 | H2: =PnL!B65*E2 | I2: =PnL!B66*E2 | J2: =PnL!B67*E2
A3: Roma | B3: 2025 | C3: 250000 | D3: 2.8 | E3: 2 | F3: 0 | G3: =PnL!B64*E3 | H3: =PnL!B65*E3 | I3: =PnL!B66*E3 | J3: =PnL!B67*E3
A4: Bologna | B4: 2026 | C4: 250000 | D4: 0.4 | E4: 0.28571429 | F4: 0 | G4: 0 | H4: =PnL!B65*E4 | I4: =PnL!B66*E4 | J4: =PnL!B67*E4
A5: Torino | B5: 2027 | C5: 250000 | D5: 0.9 | E5: 0.64285714 | F5: 0 | G5: 0 | H5: 0 | I5: =PnL!B66*E5 | J5: =PnL!B67*E5
A6: Firenze | B6: 2028 | C6: 250000 | D6: 0.4 | E6: 0.28571429 | F6: 0 | G6: 0 | H6: 0 | I6: 0 | J6: =PnL!B67*E6
A7: Total | F7: =SUM(F2:F6) | G7: =SUM(G2:G6) | H7: =SUM(H2:H6) | I7: =SUM(I2:I6) | J7: =SUM(J2:J6)

Sheet Valuation
A1: DCF Valuation
A2: Year | B2: FCF | C2: Discount Factor | D2: PV of FCF
A3: 2024 | B3: =CashFlow!J2 | C3: =1/(1+Assumptions!B13)^1 | D3: =B3*C3
A4: 2025 | B4: =CashFlow!J3 | C4: =1/(1+Assumptions!B13)^2 | D4: =B4*C4
A5: 2026 | B5: =CashFlow!J4 | C5: =1/(1+Assumptions!B13)^3 | D5: =B5*C5
A6: 2027 | B6: =CashFlow!J5 | C6: =1/(1+Assumptions!B13)^4 | D6: =B6*C6
A7: 2028 | B7: =CashFlow!J6 | C7: =1/(1+Assumptions!B13)^5 | D7: =B7*C7
A8: Terminal Value | B8: =B7*(1+Assumptions!B14)/(Assumptions!B13-Assumptions!B14) | C8: =1/(1+Assumptions!B13)^5 | D8: =B8*C8
A10: NPV of FCFs | B10: =SUM(D3:D7)
A11: NPV of TV | B11: =D8
A12: Enterprise Value | B12: =B10+B11
A13: Equity Value (no debt) | B13: =B12
A14: Initial Capex | B14: =Assumptions!B10
A15: IRR | B15: =IRR(B3:B7,-B14)
A17: Sensitivity: WACC vs Exit Multiple
A18: WACC \ Exit Multiple | B18: 6x | C18: 7x | D18: 8x | E18: 9x | F18: 10x
A19: 0.07 | B19: =B10+ (PnL!H67*6)/(1+0.07)^5 | C19: =B10+ (PnL!H67*7)/(1+0.07)^5 | D19: =B10+ (PnL!H67*8)/(1+0.07)^5 | E19: =B10+ (PnL!H67*9)/(1+0.07)^5 | F19: =B10+ (PnL!H67*10)/(1+0.07)^5
A20: 0.08 | B20: =B10+ (PnL!H67*6)/(1+0.08)^5 | C20: =B10+ (PnL!H67*7)/(1+0.08)^5 | D20: =B10+ (PnL!H67*8)/(1+0.08)^5 | E20: =B10+ (PnL!H67*9)/(1+0.08)^5 | F20: =B10+ (PnL!H67*10)/(1+0.08)^5
A21: 0.09 | B21: =B10+ (PnL!H67*6)/(1+0.09)^5 | C21: =B10+ (PnL!H67*7)/(1+0.09)^5 | D21: =B10+ (PnL!H67*8)/(1+0.09)^5 | E21: =B10+ (PnL!H67*9)/(1+0.09)^5 | F21: =B10+ (PnL!H67*10)/(1+0.09)^5
A22: 0.1 | B22: =B10+ (PnL!H67*6)/(1+0.1)^5 | C22: =B10+ (PnL!H67*7)/(1+0.1)^5 | D22: =B10+ (PnL!H67*8)/(1+0.1)^5 | E22: =B10+ (PnL!H67*9)/(1+0.1)^5 | F22: =B10+ (PnL!H67*10)/(1+0.1)^5
A23: 0.11 | B23: =B10+ (PnL!H67*6)/(1+0.11)^5 | C23: =B10+ (PnL!H67*7)/(1+0.11)^5 | D23: =B10+ (PnL!H67*8)/(1+0.11)^5 | E23: =B10+ (PnL!H67*9)/(1+0.11)^5 | F23: =B10+ (PnL!H67*10)/(1+0.11)^5

Sheet Sensitivity
A1: EBITDA Year 5 Sensitivity
A2: Scontrino \ Coperti | B2: 100 | C2: 110 | D2: 120 | E2: 130 | F2: 140 | G2: 150
A3: 16 | B3: 265497 | C3: 301646 | D3: 337796 | E3: 373945 | F3: 410095 | G3: 446245
A4: 17 | B4: 288090 | C4: 326499 | D4: 364908 | E4: 403317 | F4: 441726 | G4: 480135
A5: 18 | B5: 310684 | C5: 351352 | D5: 392020 | E5: 432689 | F5: 473357 | G5: 514025
A6: 19 | B6: 333277 | C6: 376205 | D6: 419133 | E6: 462060 | F6: 504988 | G6: 547916
A7: 20 | B7: 355871 | C7: 401058 | D7: 446245 | E7: 491432 | F7: 536619 | G7: 581806
A8: 21 | B8: 378464 | C8: 425911 | D8: 473357 | E8: 520803 | F8: 568250 | G8: 615696
A9: 22 | B9: 401058 | C9: 450763 | D9: 500469 | E9: 550175 | F9: 599881 | G9: 649587
