Workbook

Sheet Assumptions
A1: Parametro | B1: Valore | C1: Unità
A2: Prezzo vendita | B2: 2200 | C2: €/mq
A3: Costo costruzione | B3: 850 | C3: €/mq
A4: Oneri | B4: 120 | C4: €/mq
A5: Progettazione | B5: 0.05 | C5: %
A6: DL | B6: 0.03 | C6: %
A7: Collaudo | B7: 0.015 | C7: %
A8: Commercializzazione | B8: 0.03 | C8: %
A9: Oneri finanziari | B9: 0.045 | C9: %
A10: Imprevisti | B10: 0.05 | C10: %
A11: Durata | B11: 30 | C11: mesi
A12: Superficie totale | B12: 10000 | C12: mq
A13: IVA vendita | B13: 0.04 | C13: %
... A15: Debito % | B15: 0.7 | C15: %

Sheet Costi
A1: Voce di costo | B1: Importo
A2: Terreno | B2: 800000
A3: Costruzione | B3: =Assumptions!B3*Assumptions!B12
A4: Urbanizzazione | B4: =Assumptions!B4*Assumptions!B12
A5: Progettazione | B5: =Assumptions!B5*B3
A6: DL | B6: =Assumptions!B6*B3
A7: Collaudo | B7: =Assumptions!B7*B3
A8: Commercializzazione | B8: =Assumptions!B8*Ricavi!B2
A9: Oneri finanziari | B9: =Assumptions!B9*PianoFinanziario!B4
A10: Imprevisti | B10: =Assumptions!B10*(B2+B3+B4+B5+B6+B7+B8+B9)
A11: Costo Totale | B11: =SUM(B2:B10)

Sheet Ricavi
A1: Voce | B1: Importo
A2: Vendita lorda | B2: =Assumptions!B2*Assumptions!B12
A3: IVA 4% | B3: =B2*Assumptions!B13
A4: Ricavo Netto | B4: =B2-B3

Sheet PianoFinanziario
A1: Voce | B1: Importo
A2: Costo Totale | B2: =Costi!B11
A3: Equity (30%) | B3: =B2*Assumptions!B14
A4: Debito (70%) | B4: =B2*Assumptions!B15
A5: Interessi annui | B5: =B4*Assumptions!B9
A6: Rimborso | B6: =B4

Sheet Tempistiche
A1: Mese | B1: Attività | C1: Inizio | D1: Fine
A2: 1 | B2: Progettazione | C2: 1 | D2: 6
A3: 2 | B3: Permessi | C3: 4 | D3: 8
A4: 3 | B4: Scavi e fondazioni | C4: 7 | D4: 12
A5: 4 | B5: Struttura | C5: 10 | D5: 18
A6: 5 | B6: Tamponamenti | C6: 16 | D6: 22
A7: 6 | B7: Impianti | C7: 18 | D7: 26
A8: 7 | B8: Finiture | C8: 22 | D8: 28
A9: 8 | B9: Collaudo | C9: 28 | D9: 30
A10: 9 | B10: Commercializzazione | C10: 1 | D10: 30

Sheet CashFlow
A1: Mese | B1: Uscite | C1: Entrate | D1: Saldo | E1: Saldo Cumulato
A2: 1 | B2: =Costi!B11/30 | C2: =0 | D2: =C2-B2 | E2: =D2
A3: 2 | B3: =Costi!B11/30 | C3: =0 | D3: =C3-B3 | E3: =E2+D3
A4: 3 | B4: =Costi!B11/30 | C4: =0 | D4: =C4-B4 | E4: =E3+D4
A5: 4 | B5: =Costi!B11/30 | C5: =0 | D5: =C5-B5 | E5: =E4+D5
A6: 5 | B6: =Costi!B11/30 | C6: =0 | D6: =C6-B6 | E6: =E5+D6
A7: 6 | B7: =Costi!B11/30 | C7: =0 | D7: =C7-B7 | E7: =E6+D7
A8: 7 | B8: =Costi!B11/30 | C8: =0 | D8: =C8-B8 | E8: =E7+D8
A9: 8 | B9: =Costi!B11/30 | C9: =0 | D9: =C9-B9 | E9: =E8+D9
A10: 9 | B10: =Costi!B11/30 | C10: =0 | D10: =C10-B10 | E10: =E9+D10
A11: 10 | B11: =Costi!B11/30 | C11: =0 | D11: =C11-B11 | E11: =E10+D11
A12: 11 | B12: =Costi!B11/30 | C12: =0 | D12: =C12-B12 | E12: =E11+D12
A13: 12 | B13: =Costi!B11/30 | C13: =0 | D13: =C13-B13 | E13: =E12+D13
A14: 13 | B14: =Costi!B11/30 | C14: =0 | D14: =C14-B14 | E14: =E13+D14
A15: 14 | B15: =Costi!B11/30 | C15: =0 | D15: =C15-B15 | E15: =E14+D15
A16: 15 | B16: =Costi!B11/30 | C16: =0 | D16: =C16-B16 | E16: =E15+D16
A17: 16 | B17: =Costi!B11/30 | C17: =0 | D17: =C17-B17 | E17: =E16+D17
A18: 17 | B18: =Costi!B11/30 | C18: =0 | D18: =C18-B18 | E18: =E17+D18
A19: 18 | B19: =Costi!B11/30 | C19: =0 | D19: =C19-B19 | E19: =E18+D19
A20: 19 | B20: =Costi!B11/30 | C20: =0 | D20: =C20-B20 | E20: =E19+D20
A21: 20 | B21: =Costi!B11/30 | C21: =0 | D21: =C21-B21 | E21: =E20+D21
A22: 21 | B22: =Costi!B11/30 | C22: =0 | D22: =C22-B22 | E22: =E21+D22
A23: 22 | B23: =Costi!B11/30 | C23: =0 | D23: =C23-B23 | E23: =E22+D23
A24: 23 | B24: =Costi!B11/30 | C24: =0 | D24: =C24-B24 | E24: =E23+D24
A25: 24 | B25: =Costi!B11/30 | C25: =Ricavi!B4/13 | D25: =C25-B25 | E25: =E24+D25
A26: 25 | B26: =Costi!B11/30 | C26: =Ricavi!B4/13 | D26: =C26-B26 | E26: =E25+D26
A27: 26 | B27: =Costi!B11/30 | C27: =Ricavi!B4/13 | D27: =C27-B27 | E27: =E26+D27
A28: 27 | B28: =Costi!B11/30 | C28: =Ricavi!B4/13 | D28: =C28-B28 | E28: =E27+D28
A29: 28 | B29: =Costi!B11/30 | C29: =Ricavi!B4/13 | D29: =C29-B29 | E29: =E28+D29
A30: 29 | B30: =Costi!B11/30 | C30: =Ricavi!B4/13 | D30: =C30-B30 | E30: =E29+D30
A31: 30 | B31: =Costi!B11/30 | C31: =Ricavi!B4/13 | D31: =C31-B31 | E31: =E30+D31
A32: 31 | B32: =0 | C32: =Ricavi!B4/13 | D32: =C32-B32 | E32: =E31+D32
A33: 32 | B33: =0 | C33: =Ricavi!B4/13 | D33: =C33-B33 | E33: =E32+D33
A34: 33 | B34: =0 | C34: =Ricavi!B4/13 | D34: =C34-B34 | E34: =E33+D34
A35: 34 | B35: =0 | C35: =Ricavi!B4/13 | D35: =C35-B35 | E35: =E34+D35
A36: 35 | B36: =0 | C36: =Ricavi!B4/13 | D36: =C36-B36 | E36: =E35+D36
A37: 36 | B37: =0 | C37: =Ricavi!B4/13 | D37: =C37-B37 | E37: =E36+D37

Sheet ContoEconomico
A1: Voce | B1: Importo
A2: Ricavi Netti | B2: =Ricavi!B4
A3: Costi Totali | B3: =Costi!B11
A4: Utile Lordo | B4: =B2-B3
A5: Oneri Finanziari | B5: =PianoFinanziario!B5
A6: Utile Netto | B6: =B4-B5

Sheet Indici
A1: Indice | B1: Valore
A2: ROI | B2: =ContoEconomico!B4/Costi!B11
A3: ROE | B3: =ContoEconomico!B6/PianoFinanziario!B3
A4: IRR (approssimato) | B4: =ROI

Sheet Sensitivity
A1: Prezzo\Costo | B1: 2000 | C1: 2100 | D1: 2200 | E1: 2300 | F1: 2400
A2: 800 | B2: =(2000.0*Assumptions!B12 - (800.0*Assumptions!B12 + Costi!B2 + (Assumptions!B5+Assumptions!B6+Assumptions!B7)*800.0*Assumptions!B12 + Assumptions!B8*2000.0*Assumptions!B12 + Assumptions!B9*PianoFinanziario!B4 + Assumptions!B10*(Costi!B2+800.0*Assumptions!B12+Assumptions!B4*Assumptions!B12+(Assumptions!B5+Assumptions!B6+Assumptions!B7)*800.0*Assumptions!B12+Assumptions!B8*2000.0*Assumptions!B12+Assumptions!B9*PianoFinanziario!B4)))/(800.0*Assumptions!B12 + Costi!B2 + (Assumptions!B5+Assumptions!B6+Assumptions!B7)*800.0*Assumptions!B12 + Assumptions!B8*2000.0*Assumptions!B12 + Assumptions!B9*PianoFinanziario!B4 + Assumptions!B10*(Costi!B2+800.0*Assumptions!B12+Assumptions!B4*Assumptions!B12+(Assumptions!B5+Assumptions!B6+Assumptions!B7)*800.0*Assumptions!B12+Assumptions!B8*2000.0*Assumptions!B12+Assumptions!B9*PianoFinanziario!B4)) | C2: =(2100.0*Assumptions!B12 - (800.0*Assumptions!B12 + Costi!B2 + (Assumptions!B5+Assumptions!B6+Assumptions!B7)*800.0*Assumptions!B12 + Assumptions!B8*2100.0*Assumptions!B12 + Assumptions!B9*PianoFinanziario!B4 + Assumptions!B10*(Costi!B2+800.0*Assumptions!B12+Assumptions!B4*Assumptions!B12+(Assumptions!B5+Assumptions!B6+Assumptions!B7)*800.0*Assumptions!B12+Assumptions!B8*2100.0*Assumptions!B12+Assumptions!B9*PianoFinanziario!B4)))/(800.0*Assumptions!B12 + Costi!B2 + (Assumptions!B5+Assumptions!B6+Assumptions!B7)*800.0*Assumptions!B12 + Assumptions!B8*2100.0*Assumptions!B12 + Assumptions!B9*PianoFinanziario!B4 + Assumptions!B10*(Costi!B2+800.0*Assumptions!B12+Assumptions!B4*Assumptions!B12+(Assumptions!B5+Assumptions!B6+Assumptions!B7)*800.0*Assumptions!B12+Assumptions!B8*2100.0*Assumptions!B12+Assumptions!B9*PianoFinanziario!B4)) | D2: =(2200*Assumptions!B12 - (800.0*Assumptions!B12 + Costi!B2 + (Assumptions!B5+Assumptions!B6+Assumptions!B7)*800.0*Assumptions!B12 + Assumptions!B8*2200*Assumptions!B12 + Assumptions!B9*PianoFinanziario!B4 + Assumptions!B10*(Costi!B2+800.0*Assumptions!B12+Assumptions!B4*Assumptions!B12+(Assumptions!B5+Assumptions!B6+Assumptions!B7)*800.0*Assumptions!B12+Assumptions!B8*2200*Assumptions!B12+Assumptions!B9*PianoFinanziario!B4)))/(800.0*Assumptions!B12 + Costi!B2 + (Assumptions!B5+Assumptions!B6+Assumptions!B7)*800.0*Assumptions!B12 + Assumptions!B8*2200*Assumptions!B12 + Assumptions!B9*PianoFinanziario!B4 + Assumptions!B10*(Costi!B2+800.0*Assumptions!B12+Assumptions!B4*Assumptions!B12+(Assumptions!B5+Assumptions!B6+Assumptions!B7)*800.0*Assumptions!B12+Assumptions!B8*2200*Assumptions!B12+Assumptions!B9*PianoFinanziario!B4)) | E2: =(2300.0*Assumptions!B12 - (800.0*Assumptions!B12 + Costi!B2 + (Assumptions!B5+Assumptions!B6+Assumptions!B7)*800.0*Assumptions!B12 + Assumptions!B8*2300.0*Assumptions!B12 + Assumptions!B9*PianoFinanziario!B4 + Assumptions!B10*(Costi!B2+800.0*Assumptions!B12+Assumptions!B4*Assumptions!B12+(Assumptions!B5+Assumptions!B6+Assumptions!B7)*800.0*Assumptions!B12+Assumptions!B8*2300.0*Assumptions!B12+Assumptions!B9*PianoFinanziario!B4)))/(800.0*Assumptions!B12 + Costi!B2 + (Assumptions!B5+Assumptions!B6+Assumptions!B7)*800.0*Assumptions!B12 + Assumptions!B8*2300.0*Assumptions!B12 + Assumptions!B9*PianoFinanziario!B4 + Assumptions!B10*(Costi!B2+800.0*Assumptions!B12+Assumptions!B4*Assumptions!B12+(Assumptions!B5+Assumptions!B6+Assumptions!B7)*800.0*Assumptions!B12+Assumptions!B8*2300.0*Assumptions!B12+Assumptions!B9*PianoFinanziario!B4)) | F2: =(2400.0*Assumptions!B12 - (800.0*Assumptions!B12 + Costi!B2 + (Assumptions!B5+Assumptions!B6+Assumptions!B7)*800.0*Assumptions!B12 + Assumptions!B8*2400.0*Assumptions!B12 + Assumptions!B9*PianoFinanziario!B4 + Assumptions!B10*(Costi!B2+800.0*Assumptions!B12+Assumptions!B4*Assumptions!B12+(Assumptions!B5+Assumptions!B6+Assumptions!B7)*800.0*Assumptions!B12+Assumptions!B8*2400.0*Assumptions!B12+Assumptions!B9*PianoFinanziario!B4)))/(800.0*Assumptions!B12 + Costi!B2 + (Assumptions!B5+Assumptions!B6+Assumptions!B7)*800.0*Assumptions!B12 + Assumptions!B8*2400.0*Assumptions!B12 + Assumptions!B9*PianoFinanziario!B4 + Assumptions!B10*(Costi!B2+800.0*Assumptions!B12+Assumptions!B4*Assumptions!B12+(Assumptions!B5+Assumptions!B6+Assumptions!B7)*800.0*Assumptions!B12+Assumptions!B8*2400.0*Assumptions!B12+Assumptions!B9*PianoFinanziario!B4))
A3: 800 | B3: =(2000.0*Assumptions!B12 - (800.0*Assumptions!B12 + Costi!B2 + (Assumptions!B5+Assumptions!B6+Assumptions!B7)*800.0*Assumptions!B12 + Assumptions!B8*2000.0*Assumptions!B12 + Assumptions!B9*PianoFinanziario!B4 + Assumptions!B10*(Costi!B2+800.0*Assumptions!B12+Assumptions!B4*Assumptions!B12+(Assumptions!B5+Assumptions!B6+Assumptions!B7)*800.0*Assumptions!B12+Assumptions!B8*2000.0*Assumptions!B12+Assumptions!B9*PianoFinanziario!B4)))/(800.0*Assumptions!B12 + Costi!B2 + (Assumptions!B5+Assumptions!B6+Assumptions!B7)*800.0*Assumptions!B12 + Assumptions!B8*2000.0*Assumptions!B12 + Assumptions!B9*PianoFinanziario!B4 + Assumptions!B10*(Costi!B2+800.0*Assumptions!B12+Assumptions!B4*Assumptions!B12+(Assumptions!B5+Assumptions!B6+Assumptions!B7)*800.0*Assumptions!B12+Assumptions!B8*2000.0*Assumptions!B12+Assumptions!B9*PianoFinanziario!B4)) | C3: =(2100.0*Assumptions!B12 - (800.0*Assumptions!B12 + Costi!B2 + (Assumptions!B5+Assumptions!B6+Assumptions!B7)*800.0*Assumptions!B12 + Assumptions!B8*2100.0*Assumptions!B12 + Assumptions!B9*PianoFinanziario!B4 + Assumptions!B10*(Costi!B2+800.0*Assumptions!B12+Assumptions!B4*Assumptions!B12+(Assumptions!B5+Assumptions!B6+Assumptions!B7)*800.0*Assumptions!B12+Assumptions!B8*2100.0*Assumptions!B12+Assumptions!B9*PianoFinanziario!B4)))/(800.0*Assumptions!B12 + Costi!B2 + (Assumptions!B5+Assumptions!B6+Assumptions!B7)*800.0*Assumptions!B12 + Assumptions!B8*2100.0*Assumptions!B12 + Assumptions!B9*PianoFinanziario!B4 + Assumptions!B10*(Costi!B2+800.0*Assumptions!B12+Assumptions!B4*Assumptions!B12+(Assumptions!B5+Assumptions!B6+Assumptions!B7)*800.0*Assumptions!B12+Assumptions!B8*2100.0*Assumptions!B12+Assumptions!B9*PianoFinanziario!B4)) | D3: =(2200*Assumptions!B12 - (800.0*Assumptions!B12 + Costi!B2 + (Assumptions!B5+Assumptions!B6+Assumptions!B7)*800.0*Assumptions!B12 + Assumptions!B8*2200*Assumptions!B12 + Assumptions!B9*PianoFinanziario!B4 + Assumptions!B10*(Costi!B2+800.0*Assumptions!B12+Assumptions!B4*Assumptions!B12+(Assumptions!B5+Assumptions!B6+Assumptions!B7)*800.0*Assumptions!B12+Assumptions!B8*2200*Assumptions!B12+Assumptions!B9*PianoFinanziario!B4)))/(800.0*Assumptions!B12 + Costi!B2 + (Assumptions!B5+Assumptions!B6+Assumptions!B7)*800.0*Assumptions!B12 + Assumptions!B8*2200*Assumptions!B12 + Assumptions!B9*PianoFinanziario!B4 + Assumptions!B10*(Costi!B2+800.0*Assumptions!B12+Assumptions!B4*Assumptions!B12+(Assumptions!B5+Assumptions!B6+Assumptions!B7)*800.0*Assumptions!B12+Assumptions!B8*2200*Assumptions!B12+Assumptions!B9*PianoFinanziario!B4)) | E3: =(2300.0*Assumptions!B12 - (800.0*Assumptions!B12 + Costi!B2 + (Assumptions!B5+Assumptions!B6+Assumptions!B7)*800.0*Assumptions!B12 + Assumptions!B8*2300.0*Assumptions!B12 + Assumptions!B9*PianoFinanziario!B4 + Assumptions!B10*(Costi!B2+800.0*Assumptions!B12+Assumptions!B4*Assumptions!B12+(Assumptions!B5+Assumptions!B6+Assumptions!B7)*800.0*Assumptions!B12+Assumptions!B8*2300.0*Assumptions!B12+Assumptions!B9*PianoFinanziario!B4)))/(800.0*Assumptions!B12 + Costi!B2 + (Assumptions!B5+Assumptions!B6+Assumptions!B7)*800.0*Assumptions!B12 + Assumptions!B8*2300.0*Assumptions!B12 + Assumptions!B9*PianoFinanziario!B4 + Assumptions!B10*(Costi!B2+800.0*Assumptions!B12+Assumptions!B4*Assumptions!B12+(Assumptions!B5+Assumptions!B6+Assumptions!B7)*800.0*Assumptions!B12+Assumptions!B8*2300.0*Assumptions!B12+Assumptions!B9*PianoFinanziario!B4)) | F3: =(2400.0*Assumptions!B12 - (800.0*Assumptions!B12 + Costi!B2 + (Assumptions!B5+Assumptions!B6+Assumptions!B7)*800.0*Assumptions!B12 + Assumptions!B8*2400.0*Assumptions!B12 + Assumptions!B9*PianoFinanziario!B4 + Assumptions!B10*(Costi!B2+800.0*Assumptions!B12+Assumptions!B4*Assumptions!B12+(Assumptions!B5+Assumptions!B6+Assumptions!B7)*800.0*Assumptions!B12+Assumptions!B8*2400.0*Assumptions!B12+Assumptions!B9*PianoFinanziario!B4)))/(800.0*Assumptions!B12 + Costi!B2 + (Assumptions!B5+Assumptions!B6+Assumptions!B7)*800.0*Assumptions!B12 + Assumptions!B8*2400.0*Assumptions!B12 + Assumptions!B9*PianoFinanziario!B4 + Assumptions!B10*(Costi!B2+800.0*Assumptions!B12+Assumptions!B4*Assumptions!B12+(Assumptions!B5+Assumptions!B6+Assumptions!B7)*800.0*Assumptions!B12+Assumptions!B8*2400.0*Assumptions!B12+Assumptions!B9*PianoFinanziario!B4))
A4: 800 | B4: =(2000.0*Assumptions!B12 - (800*Assumptions!B12 + Costi!B2 + (Assumptions!B5+Assumptions!B6+Assumptions!B7)*800*Assumptions!B12 + Assumptions!B8*2000.0*Assumptions!B12 + Assumptions!B9*PianoFinanziario!B4 + Assumptions!B10*(Costi!B2+800*Assumptions!B12+Assumptions!B4*Assumptions!B12+(Assumptions!B5+Assumptions!B6+Assumptions!B7)*800*Assumptions!B12+Assumptions!B8*2000.0*Assumptions!B12+Assumptions!B9*PianoFinanziario!B4)))/(800*Assumptions!B12 + Costi!B2 + (Assumptions!B5+Assumptions!B6+Assumptions!B7)*800*Assumptions!B12 + Assumptions!B8*2000.0*Assumptions!B12 + Assumptions!B9*PianoFinanziario!B4 + Assumptions!B10*(Costi!B2+800*Assumptions!B12+Assumptions!B4*Assumptions!B12+(Assumptions!B5+Assumptions!B6+Assumptions!B7)*800*Assumptions!B12+Assumptions!B8*2000.0*Assumptions!B12+Assumptions!B9*PianoFinanziario!B4)) | C4: =(2100.0*Assumptions!B12 - (800*Assumptions!B12 + Costi!B2 + (Assumptions!B5+Assumptions!B6+Assumptions!B7)*800*Assumptions!B12 + Assumptions!B8*2100.0*Assumptions!B12 + Assumptions!B9*PianoFinanziario!B4 + Assumptions!B10*(Costi!B2+800*Assumptions!B12+Assumptions!B4*Assumptions!B12+(Assumptions!B5+Assumptions!B6+Assumptions!B7)*800*Assumptions!B12+Assumptions!B8*2100.0*Assumptions!B12+Assumptions!B9*PianoFinanziario!B4)))/(800*Assumptions!B12 + Costi!B2 + (Assumptions!B5+Assumptions!B6+Assumptions!B7)*800*Assumptions!B12 + Assumptions!B8*2100.0*Assumptions!B12 + Assumptions!B9*PianoFinanziario!B4 + Assumptions!B10*(Costi!B2+800*Assumptions!B12+Assumptions!B4*Assumptions!B12+(Assumptions!B5+Assumptions!B6+Assumptions!B7)*800*Assumptions!B12+Assumptions!B8*2100.0*Assumptions!B12+Assumptions!B9*PianoFinanziario!B4)) | D4: =(2200*Assumptions!B12 - (800*Assumptions!B12 + Costi!B2 + (Assumptions!B5+Assumptions!B6+Assumptions!B7)*800*Assumptions!B12 + Assumptions!B8*2200*Assumptions!B12 + Assumptions!B9*PianoFinanziario!B4 + Assumptions!B10*(Costi!B2+800*Assumptions!B12+Assumptions!B4*Assumptions!B12+(Assumptions!B5+Assumptions!B6+Assumptions!B7)*800*Assumptions!B12+Assumptions!B8*2200*Assumptions!B12+Assumptions!B9*PianoFinanziario!B4)))/(800*Assumptions!B12 + Costi!B2 + (Assumptions!B5+Assumptions!B6+Assumptions!B7)*800*Assumptions!B12 + Assumptions!B8*2200*Assumptions!B12 + Assumptions!B9*PianoFinanziario!B4 + Assumptions!B10*(Costi!B2+800*Assumptions!B12+Assumptions!B4*Assumptions!B12+(Assumptions!B5+Assumptions!B6+Assumptions!B7)*800*Assumptions!B12+Assumptions!B8*2200*Assumptions!B12+Assumptions!B9*PianoFinanziario!B4)) | E4: =(2300.0*Assumptions!B12 - (800*Assumptions!B12 + Costi!B2 + (Assumptions!B5+Assumptions!B6+Assumptions!B7)*800*Assumptions!B12 + Assumptions!B8*2300.0*Assumptions!B12 + Assumptions!B9*PianoFinanziario!B4 + Assumptions!B10*(Costi!B2+800*Assumptions!B12+Assumptions!B4*Assumptions!B12+(Assumptions!B5+Assumptions!B6+Assumptions!B7)*800*Assumptions!B12+Assumptions!B8*2300.0*Assumptions!B12+Assumptions!B9*PianoFinanziario!B4)))/(800*Assumptions!B12 + Costi!B2 + (Assumptions!B5+Assumptions!B6+Assumptions!B7)*800*Assumptions!B12 + Assumptions!B8*2300.0*Assumptions!B12 + Assumptions!B9*PianoFinanziario!B4 + Assumptions!B10*(Costi!B2+800*Assumptions!B12+Assumptions!B4*Assumptions!B12+(Assumptions!B5+Assumptions!B6+Assumptions!B7)*800*Assumptions!B12+Assumptions!B8*2300.0*Assumptions!B12+Assumptions!B9*PianoFinanziario!B4)) | F4: =(2400.0*Assumptions!B12 - (800*Assumptions!B12 + Costi!B2 + (Assumptions!B5+Assumptions!B6+Assumptions!B7)*800*Assumptions!B12 + Assumptions!B8*2400.0*Assumptions!B12 + Assumptions!B9*PianoFinanziario!B4 + Assumptions!B10*(Costi!B2+800*Assumptions!B12+Assumptions!B4*Assumptions!B12+(Assumptions!B5+Assumptions!B6+Assumptions!B7)*800*Assumptions!B12+Assumptions!B8*2400.0*Assumptions!B12+Assumptions!B9*PianoFinanziario!B4)))/(800*Assumptions!B12 + Costi!B2 + (Assumptions!B5+Assumptions!B6+Assumptions!B7)*800*Assumptions!B12 + Assumptions!B8*2400.0*Assumptions!B12 + Assumptions!B9*PianoFinanziario!B4 + Assumptions!B10*(Costi!B2+800*Assumptions!B12+Assumptions!B4*Assumptions!B12+(Assumptions!B5+Assumptions!B6+Assumptions!B7)*800*Assumptions!B12+Assumptions!B8*2400.0*Assumptions!B12+Assumptions!B9*PianoFinanziario!B4))
A5: 900 | B5: =(2000.0*Assumptions!B12 - (900.0*Assumptions!B12 + Costi!B2 + (Assumptions!B5+Assumptions!B6+Assumptions!B7)*900.0*Assumptions!B12 + Assumptions!B8*2000.0*Assumptions!B12 + Assumptions!B9*PianoFinanziario!B4 + Assumptions!B10*(Costi!B2+900.0*Assumptions!B12+Assumptions!B4*Assumptions!B12+(Assumptions!B5+Assumptions!B6+Assumptions!B7)*900.0*Assumptions!B12+Assumptions!B8*2000.0*Assumptions!B12+Assumptions!B9*PianoFinanziario!B4)))/(900.0*Assumptions!B12 + Costi!B2 + (Assumptions!B5+Assumptions!B6+Assumptions!B7)*900.0*Assumptions!B12 + Assumptions!B8*2000.0*Assumptions!B12 + Assumptions!B9*PianoFinanziario!B4 + Assumptions!B10*(Costi!B2+900.0*Assumptions!B12+Assumptions!B4*Assumptions!B12+(Assumptions!B5+Assumptions!B6+Assumptions!B7)*900.0*Assumptions!B12+Assumptions!B8*2000.0*Assumptions!B12+Assumptions!B9*PianoFinanziario!B4)) | C5: =(2100.0*Assumptions!B12 - (900.0*Assumptions!B12 + Costi!B2 + (Assumptions!B5+Assumptions!B6+Assumptions!B7)*900.0*Assumptions!B12 + Assumptions!B8*2100.0*Assumptions!B12 + Assumptions!B9*PianoFinanziario!B4 + Assumptions!B10*(Costi!B2+900.0*Assumptions!B12+Assumptions!B4*Assumptions!B12+(Assumptions!B5+Assumptions!B6+Assumptions!B7)*900.0*Assumptions!B12+Assumptions!B8*2100.0*Assumptions!B12+Assumptions!B9*PianoFinanziario!B4)))/(900.0*Assumptions!B12 + Costi!B2 + (Assumptions!B5+Assumptions!B6+Assumptions!B7)*900.0*Assumptions!B12 + Assumptions!B8*2100.0*Assumptions!B12 + Assumptions!B9*PianoFinanziario!B4 + Assumptions!B10*(Costi!B2+900.0*Assumptions!B12+Assumptions!B4*Assumptions!B12+(Assumptions!B5+Assumptions!B6+Assumptions!B7)*900.0*Assumptions!B12+Assumptions!B8*2100.0*Assumptions!B12+Assumptions!B9*PianoFinanziario!B4)) | D5: =(2200*Assumptions!B12 - (900.0*Assumptions!B12 + Costi!B2 + (Assumptions!B5+Assumptions!B6+Assumptions!B7)*900.0*Assumptions!B12 + Assumptions!B8*2200*Assumptions!B12 + Assumptions!B9*PianoFinanziario!B4 + Assumptions!B10*(Costi!B2+900.0*Assumptions!B12+Assumptions!B4*Assumptions!B12+(Assumptions!B5+Assumptions!B6+Assumptions!B7)*900.0*Assumptions!B12+Assumptions!B8*2200*Assumptions!B12+Assumptions!B9*PianoFinanziario!B4)))/(900.0*Assumptions!B12 + Costi!B2 + (Assumptions!B5+Assumptions!B6+Assumptions!B7)*900.0*Assumptions!B12 + Assumptions!B8*2200*Assumptions!B12 + Assumptions!B9*PianoFinanziario!B4 + Assumptions!B10*(Costi!B2+900.0*Assumptions!B12+Assumptions!B4*Assumptions!B12+(Assumptions!B5+Assumptions!B6+Assumptions!B7)*900.0*Assumptions!B12+Assumptions!B8*2200*Assumptions!B12+Assumptions!B9*PianoFinanziario!B4)) | E5: =(2300.0*Assumptions!B12 - (900.0*Assumptions!B12 + Costi!B2 + (Assumptions!B5+Assumptions!B6+Assumptions!B7)*900.0*Assumptions!B12 + Assumptions!B8*2300.0*Assumptions!B12 + Assumptions!B9*PianoFinanziario!B4 + Assumptions!B10*(Costi!B2+900.0*Assumptions!B12+Assumptions!B4*Assumptions!B12+(Assumptions!B5+Assumptions!B6+Assumptions!B7)*900.0*Assumptions!B12+Assumptions!B8*2300.0*Assumptions!B12+Assumptions!B9*PianoFinanziario!B4)))/(900.0*Assumptions!B12 + Costi!B2 + (Assumptions!B5+Assumptions!B6+Assumptions!B7)*900.0*Assumptions!B12 + Assumptions!B8*2300.0*Assumptions!B12 + Assumptions!B9*PianoFinanziario!B4 + Assumptions!B10*(Costi!B2+900.0*Assumptions!B12+Assumptions!B4*Assumptions!B12+(Assumptions!B5+Assumptions!B6+Assumptions!B7)*900.0*Assumptions!B12+Assumptions!B8*2300.0*Assumptions!B12+Assumptions!B9*PianoFinanziario!B4)) | F5: =(2400.0*Assumptions!B12 - (900.0*Assumptions!B12 + Costi!B2 + (Assumptions!B5+Assumptions!B6+Assumptions!B7)*900.0*Assumptions!B12 + Assumptions!B8*2400.0*Assumptions!B12 + Assumptions!B9*PianoFinanziario!B4 + Assumptions!B10*(Costi!B2+900.0*Assumptions!B12+Assumptions!B4*Assumptions!B12+(Assumptions!B5+Assumptions!B6+Assumptions!B7)*900.0*Assumptions!B12+Assumptions!B8*2400.0*Assumptions!B12+Assumptions!B9*PianoFinanziario!B4)))/(900.0*Assumptions!B12 + Costi!B2 + (Assumptions!B5+Assumptions!B6+Assumptions!B7)*900.0*Assumptions!B12 + Assumptions!B8*2400.0*Assumptions!B12 + Assumptions!B9*PianoFinanziario!B4 + Assumptions!B10*(Costi!B2+900.0*Assumptions!B12+Assumptions!B4*Assumptions!B12+(Assumptions!B5+Assumptions!B6+Assumptions!B7)*900.0*Assumptions!B12+Assumptions!B8*2400.0*Assumptions!B12+Assumptions!B9*PianoFinanziario!B4))
A6: 900 | B6: =(2000.0*Assumptions!B12 - (900.0*Assumptions!B12 + Costi!B2 + (Assumptions!B5+Assumptions!B6+Assumptions!B7)*900.0*Assumptions!B12 + Assumptions!B8*2000.0*Assumptions!B12 + Assumptions!B9*PianoFinanziario!B4 + Assumptions!B10*(Costi!B2+900.0*Assumptions!B12+Assumptions!B4*Assumptions!B12+(Assumptions!B5+Assumptions!B6+Assumptions!B7)*900.0*Assumptions!B12+Assumptions!B8*2000.0*Assumptions!B12+Assumptions!B9*PianoFinanziario!B4)))/(900.0*Assumptions!B12 + Costi!B2 + (Assumptions!B5+Assumptions!B6+Assumptions!B7)*900.0*Assumptions!B12 + Assumptions!B8*2000.0*Assumptions!B12 + Assumptions!B9*PianoFinanziario!B4 + Assumptions!B10*(Costi!B2+900.0*Assumptions!B12+Assumptions!B4*Assumptions!B12+(Assumptions!B5+Assumptions!B6+Assumptions!B7)*900.0*Assumptions!B12+Assumptions!B8*2000.0*Assumptions!B12+Assumptions!B9*PianoFinanziario!B4)) | C6: =(2100.0*Assumptions!B12 - (900.0*Assumptions!B12 + Costi!B2 + (Assumptions!B5+Assumptions!B6+Assumptions!B7)*900.0*Assumptions!B12 + Assumptions!B8*2100.0*Assumptions!B12 + Assumptions!B9*PianoFinanziario!B4 + Assumptions!B10*(Costi!B2+900.0*Assumptions!B12+Assumptions!B4*Assumptions!B12+(Assumptions!B5+Assumptions!B6+Assumptions!B7)*900.0*Assumptions!B12+Assumptions!B8*2100.0*Assumptions!B12+Assumptions!B9*PianoFinanziario!B4)))/(900.0*Assumptions!B12 + Costi!B2 + (Assumptions!B5+Assumptions!B6+Assumptions!B7)*900.0*Assumptions!B12 + Assumptions!B8*2100.0*Assumptions!B12 + Assumptions!B9*PianoFinanziario!B4 + Assumptions!B10*(Costi!B2+900.0*Assumptions!B12+Assumptions!B4*Assumptions!B12+(Assumptions!B5+Assumptions!B6+Assumptions!B7)*900.0*Assumptions!B12+Assumptions!B8*2100.0*Assumptions!B12+Assumptions!B9*PianoFinanziario!B4)) | D6: =(2200*Assumptions!B12 - (900.0*Assumptions!B12 + Costi!B2 + (Assumptions!B5+Assumptions!B6+Assumptions!B7)*900.0*Assumptions!B12 + Assumptions!B8*2200*Assumptions!B12 + Assumptions!B9*PianoFinanziario!B4 + Assumptions!B10*(Costi!B2+900.0*Assumptions!B12+Assumptions!B4*Assumptions!B12+(Assumptions!B5+Assumptions!B6+Assumptions!B7)*900.0*Assumptions!B12+Assumptions!B8*2200*Assumptions!B12+Assumptions!B9*PianoFinanziario!B4)))/(900.0*Assumptions!B12 + Costi!B2 + (Assumptions!B5+Assumptions!B6+Assumptions!B7)*900.0*Assumptions!B12 + Assumptions!B8*2200*Assumptions!B12 + Assumptions!B9*PianoFinanziario!B4 + Assumptions!B10*(Costi!B2+900.0*Assumptions!B12+Assumptions!B4*Assumptions!B12+(Assumptions!B5+Assumptions!B6+Assumptions!B7)*900.0*Assumptions!B12+Assumptions!B8*2200*Assumptions!B12+Assumptions!B9*PianoFinanziario!B4)) | E6: =(2300.0*Assumptions!B12 - (900.0*Assumptions!B12 + Costi!B2 + (Assumptions!B5+Assumptions!B6+Assumptions!B7)*900.0*Assumptions!B12 + Assumptions!B8*2300.0*Assumptions!B12 + Assumptions!B9*PianoFinanziario!B4 + Assumptions!B10*(Costi!B2+900.0*Assumptions!B12+Assumptions!B4*Assumptions!B12+(Assumptions!B5+Assumptions!B6+Assumptions!B7)*900.0*Assumptions!B12+Assumptions!B8*2300.0*Assumptions!B12+Assumptions!B9*PianoFinanziario!B4)))/(900.0*Assumptions!B12 + Costi!B2 + (Assumptions!B5+Assumptions!B6+Assumptions!B7)*900.0*Assumptions!B12 + Assumptions!B8*2300.0*Assumptions!B12 + Assumptions!B9*PianoFinanziario!B4 + Assumptions!B10*(Costi!B2+900.0*Assumptions!B12+Assumptions!B4*Assumptions!B12+(Assumptions!B5+Assumptions!B6+Assumptions!B7)*900.0*Assumptions!B12+Assumptions!B8*2300.0*Assumptions!B12+Assumptions!B9*PianoFinanziario!B4)) | F6: =(2400.0*Assumptions!B12 - (900.0*Assumptions!B12 + Costi!B2 + (Assumptions!B5+Assumptions!B6+Assumptions!B7)*900.0*Assumptions!B12 + Assumptions!B8*2400.0*Assumptions!B12 + Assumptions!B9*PianoFinanziario!B4 + Assumptions!B10*(Costi!B2+900.0*Assumptions!B12+Assumptions!B4*Assumptions!B12+(Assumptions!B5+Assumptions!B6+Assumptions!B7)*900.0*Assumptions!B12+Assumptions!B8*2400.0*Assumptions!B12+Assumptions!B9*PianoFinanziario!B4)))/(900.0*Assumptions!B12 + Costi!B2 + (Assumptions!B5+Assumptions!B6+Assumptions!B7)*900.0*Assumptions!B12 + Assumptions!B8*2400.0*Assumptions!B12 + Assumptions!B9*PianoFinanziario!B4 + Assumptions!B10*(Costi!B2+900.0*Assumptions!B12+Assumptions!B4*Assumptions!B12+(Assumptions!B5+Assumptions!B6+Assumptions!B7)*900.0*Assumptions!B12+Assumptions!B8*2400.0*Assumptions!B12+Assumptions!B9*PianoFinanziario!B4))
